{
"meta":{"test_sets":[],"test_metrics":[],"learn_metrics":[{"best_value":"Min","name":"RMSE"}],"launch_mode":"Train","parameters":"","iteration_count":1000,"learn_sets":["learn"],"name":"experiment"},
"iterations":[
{"learn":[6.439820273],"iteration":0,"passed_time":0.1559054508,"remaining_time":155.7495454},
{"learn":[6.230176682],"iteration":1,"passed_time":0.1604011882,"remaining_time":80.04019291},
{"learn":[6.045734723],"iteration":2,"passed_time":0.1622824282,"remaining_time":53.9318603},
{"learn":[5.853188604],"iteration":3,"passed_time":0.1646198034,"remaining_time":40.99033104},
{"learn":[5.719583168],"iteration":4,"passed_time":0.1752271193,"remaining_time":34.87019674},
{"learn":[5.557562945],"iteration":5,"passed_time":0.176559895,"remaining_time":29.25008927},
{"learn":[5.45631948],"iteration":6,"passed_time":0.1774980191,"remaining_time":25.17936186},
{"learn":[5.340840241],"iteration":7,"passed_time":0.1809615743,"remaining_time":22.43923521},
{"learn":[5.168283508],"iteration":8,"passed_time":0.1825545509,"remaining_time":20.10128443},
{"learn":[5.058389301],"iteration":9,"passed_time":0.1951624601,"remaining_time":19.32108355},
{"learn":[4.942920176],"iteration":10,"passed_time":0.1989709868,"remaining_time":17.88930054},
{"learn":[4.790730158],"iteration":11,"passed_time":0.2021216932,"remaining_time":16.64135274},
{"learn":[4.711459482],"iteration":12,"passed_time":0.2029709827,"remaining_time":15.41018154},
{"learn":[4.59118489],"iteration":13,"passed_time":0.2044015509,"remaining_time":14.39570923},
{"learn":[4.497755178],"iteration":14,"passed_time":0.2058648778,"remaining_time":13.51846031},
{"learn":[4.395799969],"iteration":15,"passed_time":0.2073390676,"remaining_time":12.75135266},
{"learn":[4.310151015],"iteration":16,"passed_time":0.208858349,"remaining_time":12.07692689},
{"learn":[4.22276983],"iteration":17,"passed_time":0.2103488014,"remaining_time":11.47569572},
{"learn":[4.088572589],"iteration":18,"passed_time":0.2117266595,"remaining_time":10.93178174},
{"learn":[3.993504554],"iteration":19,"passed_time":0.2132065537,"remaining_time":10.44712113},
{"learn":[3.882905059],"iteration":20,"passed_time":0.214832319,"remaining_time":10.01527811},
{"learn":[3.803495949],"iteration":21,"passed_time":0.2162452177,"remaining_time":9.613082862},
{"learn":[3.696163547],"iteration":22,"passed_time":0.218081754,"remaining_time":9.263733636},
{"learn":[3.59453],"iteration":23,"passed_time":0.226338881,"remaining_time":9.204447825},
{"learn":[3.515629423],"iteration":24,"passed_time":0.2319558649,"remaining_time":9.046278733},
{"learn":[3.440875369],"iteration":25,"passed_time":0.2338618008,"remaining_time":8.760822844},
{"learn":[3.382572344],"iteration":26,"passed_time":0.2368090792,"remaining_time":8.533897558},
{"learn":[3.326709821],"iteration":27,"passed_time":0.2382554683,"remaining_time":8.2708684},
{"learn":[3.23693471],"iteration":28,"passed_time":0.2397621778,"remaining_time":8.027899126},
{"learn":[3.155706011],"iteration":29,"passed_time":0.2459211143,"remaining_time":7.951449362},
{"learn":[3.090071771],"iteration":30,"passed_time":0.2480015934,"remaining_time":7.752049805},
{"learn":[3.026980144],"iteration":31,"passed_time":0.2487109414,"remaining_time":7.523505977},
{"learn":[2.966449431],"iteration":32,"passed_time":0.2499806185,"remaining_time":7.325189639},
{"learn":[2.897524596],"iteration":33,"passed_time":0.2512291153,"remaining_time":7.13786251},
{"learn":[2.826746126],"iteration":34,"passed_time":0.2525686883,"remaining_time":6.963679549},
{"learn":[2.755903522],"iteration":35,"passed_time":0.2547486733,"remaining_time":6.821603364},
{"learn":[2.712685678],"iteration":36,"passed_time":0.2562226916,"remaining_time":6.66871492},
{"learn":[2.675430714],"iteration":37,"passed_time":0.2575065355,"remaining_time":6.518981242},
{"learn":[2.617697287],"iteration":38,"passed_time":0.258815193,"remaining_time":6.377471806},
{"learn":[2.547387815],"iteration":39,"passed_time":0.2598911072,"remaining_time":6.237386573},
{"learn":[2.485780696],"iteration":40,"passed_time":0.2613710032,"remaining_time":6.113531513},
{"learn":[2.426799454],"iteration":41,"passed_time":0.2627408952,"remaining_time":5.992994704},
{"learn":[2.385021271],"iteration":42,"passed_time":0.2701057304,"remaining_time":6.011422884},
{"learn":[2.337238277],"iteration":43,"passed_time":0.2717839887,"remaining_time":5.905124845},
{"learn":[2.260626501],"iteration":44,"passed_time":0.2738256006,"remaining_time":5.811187745},
{"learn":[2.19127998],"iteration":45,"passed_time":0.2757710021,"remaining_time":5.719250782},
{"learn":[2.145508468],"iteration":46,"passed_time":0.2803572647,"remaining_time":5.68469092},
{"learn":[2.084332745],"iteration":47,"passed_time":0.2833528892,"remaining_time":5.619832302},
{"learn":[2.033649043],"iteration":48,"passed_time":0.2850481152,"remaining_time":5.532260359},
{"learn":[1.997359752],"iteration":49,"passed_time":0.2877920716,"remaining_time":5.468049361},
{"learn":[1.97037381],"iteration":50,"passed_time":0.2960467525,"remaining_time":5.508791531},
{"learn":[1.935142776],"iteration":51,"passed_time":0.298275881,"remaining_time":5.437798753},
{"learn":[1.893907664],"iteration":52,"passed_time":0.3001029967,"remaining_time":5.362217696},
{"learn":[1.843327983],"iteration":53,"passed_time":0.3038777557,"remaining_time":5.323488091},
{"learn":[1.816983141],"iteration":54,"passed_time":0.3076487684,"remaining_time":5.285965202},
{"learn":[1.780333581],"iteration":55,"passed_time":0.3104347607,"remaining_time":5.233043109},
{"learn":[1.757235692],"iteration":56,"passed_time":0.3115554873,"remaining_time":5.154330254},
{"learn":[1.70549722],"iteration":57,"passed_time":0.3132308614,"remaining_time":5.087301232},
{"learn":[1.661018341],"iteration":58,"passed_time":0.3279379593,"remaining_time":5.230332537},
{"learn":[1.61458963],"iteration":59,"passed_time":0.3326350799,"remaining_time":5.211282918},
{"learn":[1.586861275],"iteration":60,"passed_time":0.3348988739,"remaining_time":5.155246601},
{"learn":[1.560044174],"iteration":61,"passed_time":0.3370957337,"remaining_time":5.09993223},
{"learn":[1.518603879],"iteration":62,"passed_time":0.3405589322,"remaining_time":5.065138404},
{"learn":[1.482758821],"iteration":63,"passed_time":0.343321256,"remaining_time":5.021073369},
{"learn":[1.457425738],"iteration":64,"passed_time":0.3475755651,"remaining_time":4.99974082},
{"learn":[1.43809233],"iteration":65,"passed_time":0.3510416613,"remaining_time":4.967771388},
{"learn":[1.418443316],"iteration":66,"passed_time":0.3532378961,"remaining_time":4.918969508},
{"learn":[1.396684219],"iteration":67,"passed_time":0.3552925388,"remaining_time":4.869597738},
{"learn":[1.360525779],"iteration":68,"passed_time":0.3593054816,"remaining_time":4.848020339},
{"learn":[1.327785476],"iteration":69,"passed_time":0.3649560108,"remaining_time":4.848701286},
{"learn":[1.289700818],"iteration":70,"passed_time":0.3695746406,"remaining_time":4.835701987},
{"learn":[1.253745951],"iteration":71,"passed_time":0.3723017861,"remaining_time":4.798556354},
{"learn":[1.236331587],"iteration":72,"passed_time":0.380198969,"remaining_time":4.828006086},
{"learn":[1.217065148],"iteration":73,"passed_time":0.3821590154,"remaining_time":4.782152004},
{"learn":[1.183969334],"iteration":74,"passed_time":0.3840512726,"remaining_time":4.736632362},
{"learn":[1.164610495],"iteration":75,"passed_time":0.3864610227,"remaining_time":4.698552434},
{"learn":[1.149066782],"iteration":76,"passed_time":0.3953714785,"remaining_time":4.739323047},
{"learn":[1.133517314],"iteration":77,"passed_time":0.3973756356,"remaining_time":4.697183795},
{"learn":[1.092249842],"iteration":78,"passed_time":0.3999375233,"remaining_time":4.662562771},
{"learn":[1.053667575],"iteration":79,"passed_time":0.4022601377,"remaining_time":4.625991584},
{"learn":[1.03826276],"iteration":80,"passed_time":0.4065368881,"remaining_time":4.612437039},
{"learn":[1.023520288],"iteration":81,"passed_time":0.4115719685,"remaining_time":4.607598379},
{"learn":[1.0109904],"iteration":82,"passed_time":0.4132505141,"remaining_time":4.565671343},
{"learn":[0.9835990305],"iteration":83,"passed_time":0.4153834122,"remaining_time":4.529657209},
{"learn":[0.9717640386],"iteration":84,"passed_time":0.4181956788,"remaining_time":4.501753483},
{"learn":[0.9496618324],"iteration":85,"passed_time":0.4204317123,"remaining_time":4.468309128},
{"learn":[0.9278730563],"iteration":86,"passed_time":0.4242334007,"remaining_time":4.452012584},
{"learn":[0.8960317684],"iteration":87,"passed_time":0.4264086102,"remaining_time":4.419143778},
{"learn":[0.8664214111],"iteration":88,"passed_time":0.4282116916,"remaining_time":4.383155629},
{"learn":[0.8418551725],"iteration":89,"passed_time":0.4303802077,"remaining_time":4.351622101},
{"learn":[0.8157035937],"iteration":90,"passed_time":0.4423189463,"remaining_time":4.418328815},
{"learn":[0.7967083732],"iteration":91,"passed_time":0.4464491001,"remaining_time":4.40625851},
{"learn":[0.7774472678],"iteration":92,"passed_time":0.4538322353,"remaining_time":4.426084273},
{"learn":[0.7644358914],"iteration":93,"passed_time":0.4559326402,"remaining_time":4.394414596},
{"learn":[0.7424972249],"iteration":94,"passed_time":0.4576770034,"remaining_time":4.359975664},
{"learn":[0.7208383602],"iteration":95,"passed_time":0.4600009846,"remaining_time":4.331675938},
{"learn":[0.7007665955],"iteration":96,"passed_time":0.4621144596,"remaining_time":4.301952134},
{"learn":[0.6818695856],"iteration":97,"passed_time":0.4638097851,"remaining_time":4.268943124},
{"learn":[0.6650625403],"iteration":98,"passed_time":0.4657169472,"remaining_time":4.23849464},
{"learn":[0.6474911288],"iteration":99,"passed_time":0.4760720868,"remaining_time":4.284648781},
{"learn":[0.635628723],"iteration":100,"passed_time":0.4783134934,"remaining_time":4.257463669},
{"learn":[0.6190985898],"iteration":101,"passed_time":0.4814995788,"remaining_time":4.239084527},
{"learn":[0.6035220268],"iteration":102,"passed_time":0.4865361236,"remaining_time":4.237115562},
{"learn":[0.5889137693],"iteration":103,"passed_time":0.4891686444,"remaining_time":4.214376014},
{"learn":[0.5802148487],"iteration":104,"passed_time":0.4974212742,"remaining_time":4.239924195},
{"learn":[0.5725602334],"iteration":105,"passed_time":0.4990975507,"remaining_time":4.209369909},
{"learn":[0.5586863323],"iteration":106,"passed_time":0.5008026307,"remaining_time":4.179595787},
{"learn":[0.5441570604],"iteration":107,"passed_time":0.5084289269,"remaining_time":4.199246322},
{"learn":[0.5306054404],"iteration":108,"passed_time":0.5100007595,"remaining_time":4.168905291},
{"learn":[0.5176034645],"iteration":109,"passed_time":0.511690555,"remaining_time":4.140041763},
{"learn":[0.5081633603],"iteration":110,"passed_time":0.5134666477,"remaining_time":4.112359007},
{"learn":[0.4998525462],"iteration":111,"passed_time":0.5221518848,"remaining_time":4.139918515},
{"learn":[0.4911575154],"iteration":112,"passed_time":0.5240244816,"remaining_time":4.113360312},
{"learn":[0.4848680463],"iteration":113,"passed_time":0.5257576917,"remaining_time":4.086151884},
{"learn":[0.4767008686],"iteration":114,"passed_time":0.5285459075,"remaining_time":4.067505462},
{"learn":[0.4707328798],"iteration":115,"passed_time":0.5317325495,"remaining_time":4.052168739},
{"learn":[0.4635262551],"iteration":116,"passed_time":0.5347854241,"remaining_time":4.036030166},
{"learn":[0.4491607396],"iteration":117,"passed_time":0.53634158,"remaining_time":4.008926047},
{"learn":[0.4425613032],"iteration":118,"passed_time":0.538262897,"remaining_time":3.984954725},
{"learn":[0.4371791053],"iteration":119,"passed_time":0.5543992738,"remaining_time":4.065594675},
{"learn":[0.4320024987],"iteration":120,"passed_time":0.5560993566,"remaining_time":4.039763094},
{"learn":[0.4179702787],"iteration":121,"passed_time":0.5579489127,"remaining_time":4.015402831},
{"learn":[0.4113163658],"iteration":122,"passed_time":0.5600787633,"remaining_time":3.993407117},
{"learn":[0.3960709023],"iteration":123,"passed_time":0.5636764955,"remaining_time":3.982101694},
{"learn":[0.3899981004],"iteration":124,"passed_time":0.5892949088,"remaining_time":4.125064362},
{"learn":[0.3833222763],"iteration":125,"passed_time":0.5910183781,"remaining_time":4.09960367},
{"learn":[0.371159655],"iteration":126,"passed_time":0.5931378421,"remaining_time":4.077238867},
{"learn":[0.3642411144],"iteration":127,"passed_time":0.5951989254,"remaining_time":4.054792679},
{"learn":[0.3573851086],"iteration":128,"passed_time":0.5976904801,"remaining_time":4.035569056},
{"learn":[0.3509789267],"iteration":129,"passed_time":0.5994781839,"remaining_time":4.011892462},
{"learn":[0.3424855357],"iteration":130,"passed_time":0.6022917689,"remaining_time":3.995355322},
{"learn":[0.330273294],"iteration":131,"passed_time":0.6039048748,"remaining_time":3.971132055},
{"learn":[0.3247143608],"iteration":132,"passed_time":0.6054971068,"remaining_time":3.947112719},
{"learn":[0.3145074647],"iteration":133,"passed_time":0.6096757527,"remaining_time":3.940143297},
{"learn":[0.3093628375],"iteration":134,"passed_time":0.6113727871,"remaining_time":3.917314525},
{"learn":[0.3001644305],"iteration":135,"passed_time":0.6134309389,"remaining_time":3.897090671},
{"learn":[0.2946938727],"iteration":136,"passed_time":0.6155684857,"remaining_time":3.87763214},
{"learn":[0.2875630029],"iteration":137,"passed_time":0.62171377,"remaining_time":3.883458476},
{"learn":[0.277755893],"iteration":138,"passed_time":0.6243497543,"remaining_time":3.867375097},
{"learn":[0.2686600623],"iteration":139,"passed_time":0.6257942438,"remaining_time":3.84416464},
{"learn":[0.2648837867],"iteration":140,"passed_time":0.6271375531,"remaining_time":3.820646511},
{"learn":[0.2620973872],"iteration":141,"passed_time":0.6289030228,"remaining_time":3.799991504},
{"learn":[0.2529045873],"iteration":142,"passed_time":0.6320172916,"remaining_time":3.787684048},
{"learn":[0.2503193268],"iteration":143,"passed_time":0.6338609172,"remaining_time":3.767951008},
{"learn":[0.247864402],"iteration":144,"passed_time":0.6388953014,"remaining_time":3.767279191},
{"learn":[0.2394453898],"iteration":145,"passed_time":0.6406093931,"remaining_time":3.747126176},
{"learn":[0.2371450264],"iteration":146,"passed_time":0.6425054924,"remaining_time":3.72828017},
{"learn":[0.2308254431],"iteration":147,"passed_time":0.646063612,"remaining_time":3.719231063},
{"learn":[0.2228800502],"iteration":148,"passed_time":0.6480127361,"remaining_time":3.701066029},
{"learn":[0.2198678277],"iteration":149,"passed_time":0.6494733275,"remaining_time":3.680348856},
{"learn":[0.21349105],"iteration":150,"passed_time":0.6509479061,"remaining_time":3.659965379},
{"learn":[0.2072038157],"iteration":151,"passed_time":0.6527791987,"remaining_time":3.641820793},
{"learn":[0.2009565579],"iteration":152,"passed_time":0.6547264725,"remaining_time":3.624531518},
{"learn":[0.195268398],"iteration":153,"passed_time":0.6599976729,"remaining_time":3.625701502},
{"learn":[0.1908240673],"iteration":154,"passed_time":0.6623314724,"remaining_time":3.610774801},
{"learn":[0.1853594689],"iteration":155,"passed_time":0.6641184965,"remaining_time":3.593051353},
{"learn":[0.1824901232],"iteration":156,"passed_time":0.6661864456,"remaining_time":3.577039323},
{"learn":[0.1797563798],"iteration":157,"passed_time":0.6685240727,"remaining_time":3.562640944},
{"learn":[0.1768170496],"iteration":158,"passed_time":0.6717709401,"remaining_time":3.553203526},
{"learn":[0.1716919532],"iteration":159,"passed_time":0.6735332209,"remaining_time":3.53604941},
{"learn":[0.1692389014],"iteration":160,"passed_time":0.6756539586,"remaining_time":3.52095448},
{"learn":[0.1643233502],"iteration":161,"passed_time":0.6779016197,"remaining_time":3.50667628},
{"learn":[0.1620467542],"iteration":162,"passed_time":0.6813259345,"remaining_time":3.498587774},
{"learn":[0.1574126813],"iteration":163,"passed_time":0.6830753761,"remaining_time":3.482018381},
{"learn":[0.1529849916],"iteration":164,"passed_time":0.6851864825,"remaining_time":3.467458866},
{"learn":[0.1506452523],"iteration":165,"passed_time":0.6874379793,"remaining_time":3.453754667},
{"learn":[0.146132566],"iteration":166,"passed_time":0.6893071565,"remaining_time":3.438280607},
{"learn":[0.1442159765],"iteration":167,"passed_time":0.6947624565,"remaining_time":3.440728356},
{"learn":[0.1394830741],"iteration":168,"passed_time":0.6976323546,"remaining_time":3.430369744},
{"learn":[0.1355146825],"iteration":169,"passed_time":0.6993185507,"remaining_time":3.414319983},
{"learn":[0.1315593096],"iteration":170,"passed_time":0.7017534867,"remaining_time":3.402068073},
{"learn":[0.1287443306],"iteration":171,"passed_time":0.7088561275,"remaining_time":3.412400428},
{"learn":[0.1259971546],"iteration":172,"passed_time":0.7124207142,"remaining_time":3.405618096},
{"learn":[0.1232968789],"iteration":173,"passed_time":0.7227107351,"remaining_time":3.430799237},
{"learn":[0.1202385411],"iteration":174,"passed_time":0.7309849038,"remaining_time":3.44607169},
{"learn":[0.1180498156],"iteration":175,"passed_time":0.7328744001,"remaining_time":3.431184691},
{"learn":[0.1141924252],"iteration":176,"passed_time":0.7346477757,"remaining_time":3.415904629},
{"learn":[0.1107916957],"iteration":177,"passed_time":0.7368699718,"remaining_time":3.402848971},
{"learn":[0.1088303718],"iteration":178,"passed_time":0.738714611,"remaining_time":3.388182657},
{"learn":[0.1053775978],"iteration":179,"passed_time":0.747674879,"remaining_time":3.406074449},
{"learn":[0.1025093013],"iteration":180,"passed_time":0.749507543,"remaining_time":3.391418109},
{"learn":[0.09944817085],"iteration":181,"passed_time":0.7522104826,"remaining_time":3.380814147},
{"learn":[0.09726610697],"iteration":182,"passed_time":0.7588754524,"remaining_time":3.387984943},
{"learn":[0.09445302523],"iteration":183,"passed_time":0.7606294158,"remaining_time":3.373226105},
{"learn":[0.09150611808],"iteration":184,"passed_time":0.7625666541,"remaining_time":3.35941526},
{"learn":[0.08866298102],"iteration":185,"passed_time":0.7650900888,"remaining_time":3.348297485},
{"learn":[0.08635603269],"iteration":186,"passed_time":0.7668047353,"remaining_time":3.333755346},
{"learn":[0.08372019059],"iteration":187,"passed_time":0.7714335456,"remaining_time":3.331936378},
{"learn":[0.08109952042],"iteration":188,"passed_time":0.7731439695,"remaining_time":3.317564864},
{"learn":[0.07847768983],"iteration":189,"passed_time":0.7751633709,"remaining_time":3.304643844},
{"learn":[0.07600341148],"iteration":190,"passed_time":0.7802010051,"remaining_time":3.304621011},
{"learn":[0.07480086386],"iteration":191,"passed_time":0.7853777232,"remaining_time":3.305131252},
{"learn":[0.07250193209],"iteration":192,"passed_time":0.7876035114,"remaining_time":3.293243698},
{"learn":[0.07140161128],"iteration":193,"passed_time":0.789418526,"remaining_time":3.279749134},
{"learn":[0.07004476888],"iteration":194,"passed_time":0.7916265946,"remaining_time":3.267996967},
{"learn":[0.06907840883],"iteration":195,"passed_time":0.79390881,"remaining_time":3.256646343},
{"learn":[0.06701697819],"iteration":196,"passed_time":0.7960649103,"remaining_time":3.24487372},
{"learn":[0.06508820565],"iteration":197,"passed_time":0.7976855653,"remaining_time":3.231029411},
{"learn":[0.06422109797],"iteration":198,"passed_time":0.7995249783,"remaining_time":3.21818848},
{"learn":[0.06335436716],"iteration":199,"passed_time":0.8032163898,"remaining_time":3.212865559},
{"learn":[0.06240940591],"iteration":200,"passed_time":0.8109840426,"remaining_time":3.223762438},
{"learn":[0.06062081529],"iteration":201,"passed_time":0.8133766324,"remaining_time":3.21324036},
{"learn":[0.05976445958],"iteration":202,"passed_time":0.8186630525,"remaining_time":3.214159866},
{"learn":[0.05918581029],"iteration":203,"passed_time":0.8209571391,"remaining_time":3.203342562},
{"learn":[0.05859908187],"iteration":204,"passed_time":0.8227997509,"remaining_time":3.190857571},
{"learn":[0.05781556618],"iteration":205,"passed_time":0.8248626919,"remaining_time":3.179325133},
{"learn":[0.05727385759],"iteration":206,"passed_time":0.827308031,"remaining_time":3.169349123},
{"learn":[0.05560010418],"iteration":207,"passed_time":0.8303502151,"remaining_time":3.161718127},
{"learn":[0.05493230382],"iteration":208,"passed_time":0.8325266718,"remaining_time":3.150854533},
{"learn":[0.05324431697],"iteration":209,"passed_time":0.8347837261,"remaining_time":3.140376874},
{"learn":[0.05252569618],"iteration":210,"passed_time":0.8372419582,"remaining_time":3.130729408},
{"learn":[0.05201454997],"iteration":211,"passed_time":0.8394521618,"remaining_time":3.120227847},
{"learn":[0.05031864706],"iteration":212,"passed_time":0.8436453403,"remaining_time":3.117130905},
{"learn":[0.04871979887],"iteration":213,"passed_time":0.8459592961,"remaining_time":3.107121527},
{"learn":[0.0472127431],"iteration":214,"passed_time":0.8481053491,"remaining_time":3.096570693},
{"learn":[0.04590353899],"iteration":215,"passed_time":0.8517222799,"remaining_time":3.091436423},
{"learn":[0.04460281216],"iteration":216,"passed_time":0.8556077938,"remaining_time":3.087285265},
{"learn":[0.04405976778],"iteration":217,"passed_time":0.8573684871,"remaining_time":3.075514481},
{"learn":[0.04287138395],"iteration":218,"passed_time":0.8607356613,"remaining_time":3.069564162},
{"learn":[0.04236507634],"iteration":219,"passed_time":0.8624385706,"remaining_time":3.05773675},
{"learn":[0.0411671432],"iteration":220,"passed_time":0.8644152281,"remaining_time":3.046965895},
{"learn":[0.04000714371],"iteration":221,"passed_time":0.869976066,"remaining_time":3.048835042},
{"learn":[0.03870765786],"iteration":222,"passed_time":0.8717152312,"remaining_time":3.03732168},
{"learn":[0.03769709694],"iteration":223,"passed_time":0.8738268541,"remaining_time":3.027185887},
{"learn":[0.03676865101],"iteration":224,"passed_time":0.8881846756,"remaining_time":3.059302772},
{"learn":[0.03583621777],"iteration":225,"passed_time":0.8900263568,"remaining_time":3.048143364},
{"learn":[0.03498676064],"iteration":226,"passed_time":0.8923621253,"remaining_time":3.038748559},
{"learn":[0.03412662267],"iteration":227,"passed_time":0.893999667,"remaining_time":3.027051504},
{"learn":[0.03341968741],"iteration":228,"passed_time":0.8962718706,"remaining_time":3.017579093},
{"learn":[0.0324668047],"iteration":229,"passed_time":0.898245228,"remaining_time":3.007168807},
{"learn":[0.0315985989],"iteration":230,"passed_time":0.901409373,"remaining_time":3.000795705},
{"learn":[0.03077665566],"iteration":231,"passed_time":0.9039234429,"remaining_time":2.992298294},
{"learn":[0.03000060621],"iteration":232,"passed_time":0.9058035506,"remaining_time":2.981765336},
{"learn":[0.02919168277],"iteration":233,"passed_time":0.9140618354,"remaining_time":2.992185324},
{"learn":[0.02855937239],"iteration":234,"passed_time":0.9157197636,"remaining_time":2.980960082},
{"learn":[0.0278633937],"iteration":235,"passed_time":0.9175387572,"remaining_time":2.970337333},
{"learn":[0.02718237523],"iteration":236,"passed_time":0.9249781051,"remaining_time":2.977883098},
{"learn":[0.02661530192],"iteration":237,"passed_time":0.9265269518,"remaining_time":2.966443434},
{"learn":[0.02590534962],"iteration":238,"passed_time":0.9279592326,"remaining_time":2.954715381},
{"learn":[0.02511994383],"iteration":239,"passed_time":0.9298119483,"remaining_time":2.944404503},
{"learn":[0.02460603326],"iteration":240,"passed_time":0.9314589433,"remaining_time":2.933515925},
{"learn":[0.02401914061],"iteration":241,"passed_time":0.9335925986,"remaining_time":2.924228057},
{"learn":[0.02343245728],"iteration":242,"passed_time":0.9357442428,"remaining_time":2.91505511},
{"learn":[0.02289207849],"iteration":243,"passed_time":0.9375033886,"remaining_time":2.904723614},
{"learn":[0.02235015408],"iteration":244,"passed_time":0.9393984797,"remaining_time":2.894881029},
{"learn":[0.02186763386],"iteration":245,"passed_time":0.9539321903,"remaining_time":2.923840941},
{"learn":[0.02127472323],"iteration":246,"passed_time":0.9557756398,"remaining_time":2.913761363},
{"learn":[0.02072391465],"iteration":247,"passed_time":0.9583295193,"remaining_time":2.905902413},
{"learn":[0.02026700383],"iteration":248,"passed_time":0.9615855536,"remaining_time":2.900203818},
{"learn":[0.02007185173],"iteration":249,"passed_time":0.9642898819,"remaining_time":2.892869646},
{"learn":[0.01969420495],"iteration":250,"passed_time":0.9662175756,"remaining_time":2.883254837},
{"learn":[0.01914388618],"iteration":251,"passed_time":0.9766990848,"remaining_time":2.899090934},
{"learn":[0.01867200107],"iteration":252,"passed_time":0.9800056969,"remaining_time":2.893534607},
{"learn":[0.01812086308],"iteration":253,"passed_time":0.9863434722,"remaining_time":2.896898544},
{"learn":[0.0175962171],"iteration":254,"passed_time":0.9886935215,"remaining_time":2.888535975},
{"learn":[0.01711320682],"iteration":255,"passed_time":0.9903368733,"remaining_time":2.878166538},
{"learn":[0.01662694861],"iteration":256,"passed_time":0.9962094423,"remaining_time":2.88009189},
{"learn":[0.01617582993],"iteration":257,"passed_time":1.000728203,"remaining_time":2.878063282},
{"learn":[0.01581533231],"iteration":258,"passed_time":1.002389715,"remaining_time":2.867840845},
{"learn":[0.01547325208],"iteration":259,"passed_time":1.003904376,"remaining_time":2.857266302},
{"learn":[0.01516159308],"iteration":260,"passed_time":1.005341063,"remaining_time":2.846540404},
{"learn":[0.014768205],"iteration":261,"passed_time":1.006843249,"remaining_time":2.836069914},
{"learn":[0.0144625614],"iteration":262,"passed_time":1.008386465,"remaining_time":2.825782603},
{"learn":[0.01399827195],"iteration":263,"passed_time":1.009946513,"remaining_time":2.815608461},
{"learn":[0.01346810113],"iteration":264,"passed_time":1.011543026,"remaining_time":2.805600469},
{"learn":[0.01305738183],"iteration":265,"passed_time":1.013174987,"remaining_time":2.795753535},
{"learn":[0.01257893317],"iteration":266,"passed_time":1.014787093,"remaining_time":2.785913631},
{"learn":[0.01232657868],"iteration":267,"passed_time":1.024551953,"remaining_time":2.798403095},
{"learn":[0.01206549147],"iteration":268,"passed_time":1.026179478,"remaining_time":2.788614121},
{"learn":[0.01181104809],"iteration":269,"passed_time":1.027789564,"remaining_time":2.778838451},
{"learn":[0.01145446353],"iteration":270,"passed_time":1.029385285,"remaining_time":2.769084401},
{"learn":[0.0111500112],"iteration":271,"passed_time":1.03104387,"remaining_time":2.759558594},
{"learn":[0.01085723613],"iteration":272,"passed_time":1.03656837,"remaining_time":2.760385366},
{"learn":[0.01054373425],"iteration":273,"passed_time":1.03803666,"remaining_time":2.750418304},
{"learn":[0.01043818022],"iteration":274,"passed_time":1.03959776,"remaining_time":2.74075773},
{"learn":[0.0101421741],"iteration":275,"passed_time":1.041144335,"remaining_time":2.731117749},
{"learn":[0.009876506246],"iteration":276,"passed_time":1.043446357,"remaining_time":2.723508},
{"learn":[0.009627212637],"iteration":277,"passed_time":1.046130052,"remaining_time":2.71692769},
{"learn":[0.009368876561],"iteration":278,"passed_time":1.04773093,"remaining_time":2.707577063},
{"learn":[0.009088792598],"iteration":279,"passed_time":1.049271855,"remaining_time":2.698127626},
{"learn":[0.008820895007],"iteration":280,"passed_time":1.051031121,"remaining_time":2.689293152},
{"learn":[0.008588230772],"iteration":281,"passed_time":1.052657653,"remaining_time":2.680170905},
{"learn":[0.008351508294],"iteration":282,"passed_time":1.056144367,"remaining_time":2.675814527},
{"learn":[0.008107222006],"iteration":283,"passed_time":1.057783345,"remaining_time":2.666805898},
{"learn":[0.007915427666],"iteration":284,"passed_time":1.059443888,"remaining_time":2.657903087},
{"learn":[0.007756889456],"iteration":285,"passed_time":1.061828907,"remaining_time":2.650859578},
{"learn":[0.007531958664],"iteration":286,"passed_time":1.06333754,"remaining_time":2.641671309},
{"learn":[0.007337432065],"iteration":287,"passed_time":1.064854835,"remaining_time":2.632557786},
{"learn":[0.007126524113],"iteration":288,"passed_time":1.071427761,"remaining_time":2.635934734},
{"learn":[0.006966479036],"iteration":289,"passed_time":1.07293954,"remaining_time":2.626851977},
{"learn":[0.006791357159],"iteration":290,"passed_time":1.075062791,"remaining_time":2.619311061},
{"learn":[0.006631458091],"iteration":291,"passed_time":1.079579453,"remaining_time":2.617610455},
{"learn":[0.006444469215],"iteration":292,"passed_time":1.083437941,"remaining_time":2.614302472},
{"learn":[0.006258414948],"iteration":293,"passed_time":1.085115927,"remaining_time":2.605754574},
{"learn":[0.006089006511],"iteration":294,"passed_time":1.089791995,"remaining_time":2.604418158},
{"learn":[0.005958580663],"iteration":295,"passed_time":1.09194645,"remaining_time":2.597061826},
{"learn":[0.005835926546],"iteration":296,"passed_time":1.093495104,"remaining_time":2.588306593},
{"learn":[0.005717068755],"iteration":297,"passed_time":1.095117844,"remaining_time":2.579774249},
{"learn":[0.005561787431],"iteration":298,"passed_time":1.100848437,"remaining_time":2.58091891},
{"learn":[0.005452601179],"iteration":299,"passed_time":1.102951534,"remaining_time":2.573553579},
{"learn":[0.005314320277],"iteration":300,"passed_time":1.104667974,"remaining_time":2.565325295},
{"learn":[0.005260289405],"iteration":301,"passed_time":1.106134359,"remaining_time":2.556562195},
{"learn":[0.00511597407],"iteration":302,"passed_time":1.108347709,"remaining_time":2.549565522},
{"learn":[0.004980344667],"iteration":303,"passed_time":1.109930897,"remaining_time":2.54115758},
{"learn":[0.00484920864],"iteration":304,"passed_time":1.11177204,"remaining_time":2.53338219},
{"learn":[0.004748776743],"iteration":305,"passed_time":1.113473901,"remaining_time":2.525329697},
{"learn":[0.004630862215],"iteration":306,"passed_time":1.115166752,"remaining_time":2.517298239},
{"learn":[0.004481445746],"iteration":307,"passed_time":1.120341354,"remaining_time":2.517130576},
{"learn":[0.00437181197],"iteration":308,"passed_time":1.122629602,"remaining_time":2.510475905},
{"learn":[0.004232989624],"iteration":309,"passed_time":1.124226512,"remaining_time":2.502310623},
{"learn":[0.004190402058],"iteration":310,"passed_time":1.127574234,"remaining_time":2.498066391},
{"learn":[0.004089619689],"iteration":311,"passed_time":1.129391589,"remaining_time":2.490453248},
{"learn":[0.003967272947],"iteration":312,"passed_time":1.13126077,"remaining_time":2.482990892},
{"learn":[0.003840232231],"iteration":313,"passed_time":1.138128566,"remaining_time":2.486484701},
{"learn":[0.003713626709],"iteration":314,"passed_time":1.14236645,"remaining_time":2.484193708},
{"learn":[0.003625453369],"iteration":315,"passed_time":1.144827402,"remaining_time":2.478044123},
{"learn":[0.00350961648],"iteration":316,"passed_time":1.148428127,"remaining_time":2.474373537},
{"learn":[0.003400769631],"iteration":317,"passed_time":1.164972969,"remaining_time":2.49846404},
{"learn":[0.003296640104],"iteration":318,"passed_time":1.168029031,"remaining_time":2.493503982},
{"learn":[0.003197708211],"iteration":319,"passed_time":1.170580885,"remaining_time":2.487484381},
{"learn":[0.003103127914],"iteration":320,"passed_time":1.173094768,"remaining_time":2.481406067},
{"learn":[0.003027620031],"iteration":321,"passed_time":1.174666816,"remaining_time":2.473366774},
{"learn":[0.002939921181],"iteration":322,"passed_time":1.176137033,"remaining_time":2.465154092},
{"learn":[0.002855821385],"iteration":323,"passed_time":1.178501033,"remaining_time":2.458847835},
{"learn":[0.002779885357],"iteration":324,"passed_time":1.18055206,"remaining_time":2.451915817},
{"learn":[0.00270680815],"iteration":325,"passed_time":1.183227672,"remaining_time":2.446305063},
{"learn":[0.002636466165],"iteration":326,"passed_time":1.184794475,"remaining_time":2.43843022},
{"learn":[0.00256874276],"iteration":327,"passed_time":1.186572834,"remaining_time":2.43102727},
{"learn":[0.002503527784],"iteration":328,"passed_time":1.188590464,"remaining_time":2.424146508},
{"learn":[0.002422055804],"iteration":329,"passed_time":1.190872014,"remaining_time":2.417831059},
{"learn":[0.002361792427],"iteration":330,"passed_time":1.19279149,"remaining_time":2.410808177},
{"learn":[0.002303734726],"iteration":331,"passed_time":1.196918238,"remaining_time":2.408257177},
{"learn":[0.002268421007],"iteration":332,"passed_time":1.202497153,"remaining_time":2.408605408},
{"learn":[0.002213202658],"iteration":333,"passed_time":1.205116255,"remaining_time":2.403016245},
{"learn":[0.002159862863],"iteration":334,"passed_time":1.206846522,"remaining_time":2.395680409},
{"learn":[0.002108450223],"iteration":335,"passed_time":1.210766111,"remaining_time":2.392704457},
{"learn":[0.002077799837],"iteration":336,"passed_time":1.21809237,"remaining_time":2.396425048},
{"learn":[0.002029113906],"iteration":337,"passed_time":1.220258516,"remaining_time":2.38997378},
{"learn":[0.00197058191],"iteration":338,"passed_time":1.222219511,"remaining_time":2.383147778},
{"learn":[0.001924802953],"iteration":339,"passed_time":1.228664725,"remaining_time":2.385055054},
{"learn":[0.001870355496],"iteration":340,"passed_time":1.230691035,"remaining_time":2.378373583},
{"learn":[0.001823754336],"iteration":341,"passed_time":1.232245298,"remaining_time":2.37081113},
{"learn":[0.001772575711],"iteration":342,"passed_time":1.234613436,"remaining_time":2.364842646},
{"learn":[0.001731535223],"iteration":343,"passed_time":1.236197475,"remaining_time":2.357399835},
{"learn":[0.001691969976],"iteration":344,"passed_time":1.239670709,"remaining_time":2.353577722},
{"learn":[0.001643726743],"iteration":345,"passed_time":1.242413752,"remaining_time":2.348377438},
{"learn":[0.001598494479],"iteration":346,"passed_time":1.244181226,"remaining_time":2.341355448},
{"learn":[0.001562385423],"iteration":347,"passed_time":1.246222702,"remaining_time":2.334877016},
{"learn":[0.001525164149],"iteration":348,"passed_time":1.259637348,"remaining_time":2.349638721},
{"learn":[0.001491062886],"iteration":349,"passed_time":1.261477696,"remaining_time":2.342744292},
{"learn":[0.001456060039],"iteration":350,"passed_time":1.263060371,"remaining_time":2.335402225},
{"learn":[0.001423834924],"iteration":351,"passed_time":1.265181877,"remaining_time":2.329084819},
{"learn":[0.001390911758],"iteration":352,"passed_time":1.266966942,"remaining_time":2.322174537},
{"learn":[0.0013604522],"iteration":353,"passed_time":1.269528033,"remaining_time":2.316709349},
{"learn":[0.001329478712],"iteration":354,"passed_time":1.27179942,"remaining_time":2.310734158},
{"learn":[0.001300637533],"iteration":355,"passed_time":1.273748162,"remaining_time":2.304196114},
{"learn":[0.001268934046],"iteration":356,"passed_time":1.279452421,"remaining_time":2.304447917},
{"learn":[0.001240523089],"iteration":357,"passed_time":1.282121073,"remaining_time":2.299222707},
{"learn":[0.001213334385],"iteration":358,"passed_time":1.283714943,"remaining_time":2.292092698},
{"learn":[0.001184011706],"iteration":359,"passed_time":1.28614898,"remaining_time":2.286487076},
{"learn":[0.001158435553],"iteration":360,"passed_time":1.287960827,"remaining_time":2.279797697},
{"learn":[0.001129397111],"iteration":361,"passed_time":1.289684435,"remaining_time":2.27297975},
{"learn":[0.001101309795],"iteration":362,"passed_time":1.29313797,"remaining_time":2.269225584},
{"learn":[0.001078603879],"iteration":363,"passed_time":1.295514834,"remaining_time":2.263591853},
{"learn":[0.00104740678],"iteration":364,"passed_time":1.298179582,"remaining_time":2.258476808},
{"learn":[0.001010757198],"iteration":365,"passed_time":1.302644312,"remaining_time":2.256493153},
{"learn":[0.0009829175057],"iteration":366,"passed_time":1.304931435,"remaining_time":2.25074005},
{"learn":[0.0009562286391],"iteration":367,"passed_time":1.307954954,"remaining_time":2.246270465},
{"learn":[0.0009312499265],"iteration":368,"passed_time":1.310262532,"remaining_time":2.240584438},
{"learn":[0.000905885744],"iteration":369,"passed_time":1.312249361,"remaining_time":2.234370533},
{"learn":[0.0008856410731],"iteration":370,"passed_time":1.313825593,"remaining_time":2.227483283},
{"learn":[0.000866267772],"iteration":371,"passed_time":1.315546507,"remaining_time":2.220868835},
{"learn":[0.0008477319195],"iteration":372,"passed_time":1.317847903,"remaining_time":2.215256395},
{"learn":[0.0008254703662],"iteration":373,"passed_time":1.325905297,"remaining_time":2.219296031},
{"learn":[0.0008073997745],"iteration":374,"passed_time":1.328871827,"remaining_time":2.214786378},
{"learn":[0.0007853195294],"iteration":375,"passed_time":1.330707046,"remaining_time":2.208407438},
{"learn":[0.0007642187902],"iteration":376,"passed_time":1.339279704,"remaining_time":2.213186354},
{"learn":[0.0007483657138],"iteration":377,"passed_time":1.34218279,"remaining_time":2.208565332},
{"learn":[0.0007250924046],"iteration":378,"passed_time":1.345106312,"remaining_time":2.20398686},
{"learn":[0.0007073810745],"iteration":379,"passed_time":1.350626836,"remaining_time":2.203654311},
{"learn":[0.0006903351695],"iteration":380,"passed_time":1.352219368,"remaining_time":2.196912832},
{"learn":[0.0006739314663],"iteration":381,"passed_time":1.353877744,"remaining_time":2.190304833},
{"learn":[0.0006577450475],"iteration":382,"passed_time":1.356372235,"remaining_time":2.185069632},
{"learn":[0.0006422580188],"iteration":383,"passed_time":1.364340204,"remaining_time":2.188629077},
{"learn":[0.0006272292532],"iteration":384,"passed_time":1.366631923,"remaining_time":2.183061383},
{"learn":[0.000613273061],"iteration":385,"passed_time":1.368383824,"remaining_time":2.17665199},
{"learn":[0.0005998968662],"iteration":386,"passed_time":1.370287322,"remaining_time":2.170506792},
{"learn":[0.0005825546943],"iteration":387,"passed_time":1.374707972,"remaining_time":2.168353811},
{"learn":[0.0005640029181],"iteration":388,"passed_time":1.376438675,"remaining_time":2.161964088},
{"learn":[0.0005465957475],"iteration":389,"passed_time":1.379338026,"remaining_time":2.157426143},
{"learn":[0.0005357725398],"iteration":390,"passed_time":1.381044931,"remaining_time":2.151039292},
{"learn":[0.0005221731732],"iteration":391,"passed_time":1.390228886,"remaining_time":2.156273375},
{"learn":[0.0005065959434],"iteration":392,"passed_time":1.392255824,"remaining_time":2.150379861},
{"learn":[0.0004902339346],"iteration":393,"passed_time":1.394042892,"remaining_time":2.144137037},
{"learn":[0.000474846561],"iteration":394,"passed_time":1.396539667,"remaining_time":2.139003794},
{"learn":[0.0004631775315],"iteration":395,"passed_time":1.398318294,"remaining_time":2.132788509},
{"learn":[0.0004490597218],"iteration":396,"passed_time":1.401841193,"remaining_time":2.129244936},
{"learn":[0.0004357866734],"iteration":397,"passed_time":1.403876831,"remaining_time":2.123451891},
{"learn":[0.0004248463625],"iteration":398,"passed_time":1.405612429,"remaining_time":2.117225739},
{"learn":[0.0004115592523],"iteration":399,"passed_time":1.408466119,"remaining_time":2.112699178},
{"learn":[0.0004030979495],"iteration":400,"passed_time":1.414209243,"remaining_time":2.112497099},
{"learn":[0.0003943782376],"iteration":401,"passed_time":1.41593465,"remaining_time":2.106290848},
{"learn":[0.0003843392901],"iteration":402,"passed_time":1.417567135,"remaining_time":2.09996918},
{"learn":[0.0003748782459],"iteration":403,"passed_time":1.433303191,"remaining_time":2.114476985},
{"learn":[0.0003627313557],"iteration":404,"passed_time":1.435411263,"remaining_time":2.108814078},
{"learn":[0.0003554862051],"iteration":405,"passed_time":1.437014602,"remaining_time":2.10243023},
{"learn":[0.0003446192598],"iteration":406,"passed_time":1.438932121,"remaining_time":2.096527636},
{"learn":[0.0003363604134],"iteration":407,"passed_time":1.440617853,"remaining_time":2.090308257},
{"learn":[0.0003274315396],"iteration":408,"passed_time":1.442335559,"remaining_time":2.08415725},
{"learn":[0.0003171224016],"iteration":409,"passed_time":1.445669044,"remaining_time":2.080353015},
{"learn":[0.0003093308529],"iteration":410,"passed_time":1.455944044,"remaining_time":2.086498885},
{"learn":[0.0003008468274],"iteration":411,"passed_time":1.460246191,"remaining_time":2.084040681},
{"learn":[0.0002941062699],"iteration":412,"passed_time":1.462387774,"remaining_time":2.07850272},
{"learn":[0.0002859711736],"iteration":413,"passed_time":1.464562689,"remaining_time":2.073028348},
{"learn":[0.0002782270973],"iteration":414,"passed_time":1.467481238,"remaining_time":2.068618131},
{"learn":[0.0002682660321],"iteration":415,"passed_time":1.47092663,"remaining_time":2.064954692},
{"learn":[0.0002612262848],"iteration":416,"passed_time":1.472631795,"remaining_time":2.058859321},
{"learn":[0.0002521951656],"iteration":417,"passed_time":1.474288401,"remaining_time":2.052717344},
{"learn":[0.0002437718015],"iteration":418,"passed_time":1.484655333,"remaining_time":2.058674817},
{"learn":[0.0002359120494],"iteration":419,"passed_time":1.486280243,"remaining_time":2.052482241},
{"learn":[0.0002289261557],"iteration":420,"passed_time":1.487917736,"remaining_time":2.046328667},
{"learn":[0.0002232078676],"iteration":421,"passed_time":1.49009145,"remaining_time":2.040930943},
{"learn":[0.0002210058609],"iteration":422,"passed_time":1.491736659,"remaining_time":2.034827547},
{"learn":[0.0002188990337],"iteration":423,"passed_time":1.496414081,"remaining_time":2.032864412},
{"learn":[0.0002133831396],"iteration":424,"passed_time":1.498296731,"remaining_time":2.027107342},
{"learn":[0.0002081764048],"iteration":425,"passed_time":1.500027841,"remaining_time":2.021164275},
{"learn":[0.0002030243987],"iteration":426,"passed_time":1.502480025,"remaining_time":2.016208559},
{"learn":[0.0001980729892],"iteration":427,"passed_time":1.505688463,"remaining_time":2.012275236},
{"learn":[0.000193138052],"iteration":428,"passed_time":1.507853613,"remaining_time":2.006956674},
{"learn":[0.0001887968417],"iteration":429,"passed_time":1.509386504,"remaining_time":2.000814668},
{"learn":[0.0001842884696],"iteration":430,"passed_time":1.511598767,"remaining_time":1.995590948},
{"learn":[0.0001798732728],"iteration":431,"passed_time":1.513334016,"remaining_time":1.989753984},
{"learn":[0.0001759199157],"iteration":432,"passed_time":1.522599343,"remaining_time":1.993796368},
{"learn":[0.0001713970494],"iteration":433,"passed_time":1.524241616,"remaining_time":1.98783584},
{"learn":[0.0001664503985],"iteration":434,"passed_time":1.527023755,"remaining_time":1.983375682},
{"learn":[0.0001628227628],"iteration":435,"passed_time":1.53205895,"remaining_time":1.981837724},
{"learn":[0.0001586952163],"iteration":436,"passed_time":1.534131857,"remaining_time":1.976467358},
{"learn":[0.0001546119069],"iteration":437,"passed_time":1.535833117,"remaining_time":1.970635187},
{"learn":[0.0001510000877],"iteration":438,"passed_time":1.538649687,"remaining_time":1.966247094},
{"learn":[0.0001473543603],"iteration":439,"passed_time":1.540308819,"remaining_time":1.960393043},
{"learn":[0.0001438726843],"iteration":440,"passed_time":1.543953744,"remaining_time":1.957075154},
{"learn":[0.0001400876468],"iteration":441,"passed_time":1.54767289,"remaining_time":1.953849486},
{"learn":[0.0001368098394],"iteration":442,"passed_time":1.556528128,"remaining_time":1.957079385},
{"learn":[0.0001329326463],"iteration":443,"passed_time":1.558367693,"remaining_time":1.951469453},
{"learn":[0.0001297660974],"iteration":444,"passed_time":1.560948935,"remaining_time":1.946801481},
{"learn":[0.0001261638446],"iteration":445,"passed_time":1.56267468,"remaining_time":1.941080208},
{"learn":[0.0001227434393],"iteration":446,"passed_time":1.564448293,"remaining_time":1.935436031},
{"learn":[0.0001198725647],"iteration":447,"passed_time":1.570301419,"remaining_time":1.934835677},
{"learn":[0.0001166966756],"iteration":448,"passed_time":1.57252671,"remaining_time":1.929759949},
{"learn":[0.0001131151327],"iteration":449,"passed_time":1.573805066,"remaining_time":1.923539526},
{"learn":[0.0001102581381],"iteration":450,"passed_time":1.575653215,"remaining_time":1.918034623},
{"learn":[0.0001075811536],"iteration":451,"passed_time":1.58148747,"remaining_time":1.917378615},
{"learn":[0.0001044047489],"iteration":452,"passed_time":1.584024108,"remaining_time":1.912717853},
{"learn":[0.0001019523446],"iteration":453,"passed_time":1.585892374,"remaining_time":1.907262635},
{"learn":[9.96547294e-05],"iteration":454,"passed_time":1.588186111,"remaining_time":1.902332815},
{"learn":[9.683414863e-05],"iteration":455,"passed_time":1.590025236,"remaining_time":1.896872211},
{"learn":[9.475025622e-05],"iteration":456,"passed_time":1.591638995,"remaining_time":1.891159681},
{"learn":[9.279452014e-05],"iteration":457,"passed_time":1.593679199,"remaining_time":1.885969707},
{"learn":[9.08436337e-05],"iteration":458,"passed_time":1.597389079,"remaining_time":1.88276142},
{"learn":[8.860279835e-05],"iteration":459,"passed_time":1.598919481,"remaining_time":1.876992434},
{"learn":[8.592421551e-05],"iteration":460,"passed_time":1.600540695,"remaining_time":1.871348014},
{"learn":[8.351627815e-05],"iteration":461,"passed_time":1.602553555,"remaining_time":1.866177083},
{"learn":[8.168708744e-05],"iteration":462,"passed_time":1.607387925,"remaining_time":1.864292258},
{"learn":[7.969173595e-05],"iteration":463,"passed_time":1.609320961,"remaining_time":1.859043179},
{"learn":[7.731832165e-05],"iteration":464,"passed_time":1.610883767,"remaining_time":1.853382398},
{"learn":[7.52993054e-05],"iteration":465,"passed_time":1.612765113,"remaining_time":1.848104229},
{"learn":[7.367653517e-05],"iteration":466,"passed_time":1.614859881,"remaining_time":1.843084189},
{"learn":[7.215947543e-05],"iteration":467,"passed_time":1.616542955,"remaining_time":1.837608658},
{"learn":[7.031972089e-05],"iteration":468,"passed_time":1.620862911,"remaining_time":1.835134766},
{"learn":[6.85495238e-05],"iteration":469,"passed_time":1.622821066,"remaining_time":1.829989712},
{"learn":[6.68461453e-05],"iteration":470,"passed_time":1.624492678,"remaining_time":1.824536362},
{"learn":[6.520697548e-05],"iteration":471,"passed_time":1.626055795,"remaining_time":1.818977669},
{"learn":[6.362952636e-05],"iteration":472,"passed_time":1.628001792,"remaining_time":1.813862461},
{"learn":[6.202044378e-05],"iteration":473,"passed_time":1.631923006,"remaining_time":1.810952534},
{"learn":[6.041163639e-05],"iteration":474,"passed_time":1.633603958,"remaining_time":1.80556227},
{"learn":[5.890279747e-05],"iteration":475,"passed_time":1.63725397,"remaining_time":1.802355211},
{"learn":[5.749456717e-05],"iteration":476,"passed_time":1.639763047,"remaining_time":1.797895333},
{"learn":[5.618648098e-05],"iteration":477,"passed_time":1.641411669,"remaining_time":1.792503957},
{"learn":[5.427476399e-05],"iteration":478,"passed_time":1.644736961,"remaining_time":1.788951892},
{"learn":[5.292874293e-05],"iteration":479,"passed_time":1.647944474,"remaining_time":1.78527318},
{"learn":[5.156029891e-05],"iteration":480,"passed_time":1.652195031,"remaining_time":1.782721873},
{"learn":[4.995091405e-05],"iteration":481,"passed_time":1.654434442,"remaining_time":1.77800216},
{"learn":[4.900938851e-05],"iteration":482,"passed_time":1.656160146,"remaining_time":1.772742848},
{"learn":[4.761015439e-05],"iteration":483,"passed_time":1.658251264,"remaining_time":1.767887711},
{"learn":[4.646259166e-05],"iteration":484,"passed_time":1.660037156,"remaining_time":1.762719867},
{"learn":[4.516223175e-05],"iteration":485,"passed_time":1.66510237,"remaining_time":1.761034194},
{"learn":[4.431033967e-05],"iteration":486,"passed_time":1.666793004,"remaining_time":1.7557799},
{"learn":[4.308235122e-05],"iteration":487,"passed_time":1.668534188,"remaining_time":1.750593246},
{"learn":[4.189027566e-05],"iteration":488,"passed_time":1.672442059,"remaining_time":1.747684851},
{"learn":[4.077759043e-05],"iteration":489,"passed_time":1.675406119,"remaining_time":1.743790042},
{"learn":[3.938259033e-05],"iteration":490,"passed_time":1.677973469,"remaining_time":1.739487772},
{"learn":[3.824589514e-05],"iteration":491,"passed_time":1.679672903,"remaining_time":1.734296412},
{"learn":[3.740340128e-05],"iteration":492,"passed_time":1.682730518,"remaining_time":1.730515969},
{"learn":[3.692706394e-05],"iteration":493,"passed_time":1.684402406,"remaining_time":1.725319064},
{"learn":[3.635403825e-05],"iteration":494,"passed_time":1.68633359,"remaining_time":1.720400935},
{"learn":[3.558351834e-05],"iteration":495,"passed_time":1.688317532,"remaining_time":1.71554846},
{"learn":[3.505217951e-05],"iteration":496,"passed_time":1.690022653,"remaining_time":1.710425341},
{"learn":[3.416399663e-05],"iteration":497,"passed_time":1.69139595,"remaining_time":1.704981459},
{"learn":[3.324084751e-05],"iteration":498,"passed_time":1.693408424,"remaining_time":1.700195632},
{"learn":[3.251773786e-05],"iteration":499,"passed_time":1.695067584,"remaining_time":1.695067584},
{"learn":[3.202501139e-05],"iteration":500,"passed_time":1.699600135,"remaining_time":1.692815304},
{"learn":[3.126107282e-05],"iteration":501,"passed_time":1.70106904,"remaining_time":1.687514705},
{"learn":[3.059027903e-05],"iteration":502,"passed_time":1.707931397,"remaining_time":1.687558458},
{"learn":[2.983719387e-05],"iteration":503,"passed_time":1.713081717,"remaining_time":1.685889943},
{"learn":[2.904228789e-05],"iteration":504,"passed_time":1.715333985,"remaining_time":1.681366976},
{"learn":[2.827359242e-05],"iteration":505,"passed_time":1.716863919,"remaining_time":1.676147778},
{"learn":[2.753217045e-05],"iteration":506,"passed_time":1.71838582,"remaining_time":1.670935324},
{"learn":[2.683062745e-05],"iteration":507,"passed_time":1.720383888,"remaining_time":1.666198569},
{"learn":[2.615615308e-05],"iteration":508,"passed_time":1.722172198,"remaining_time":1.661270234},
{"learn":[2.544605548e-05],"iteration":509,"passed_time":1.725771081,"remaining_time":1.658093784},
{"learn":[2.48490928e-05],"iteration":510,"passed_time":1.730033226,"remaining_time":1.655550386},
{"learn":[2.447558929e-05],"iteration":511,"passed_time":1.73166813,"remaining_time":1.650496187},
{"learn":[2.410438956e-05],"iteration":512,"passed_time":1.733385413,"remaining_time":1.64553352},
{"learn":[2.316002139e-05],"iteration":513,"passed_time":1.73574653,"remaining_time":1.641192245},
{"learn":[2.262476439e-05],"iteration":514,"passed_time":1.739829583,"remaining_time":1.638480286},
{"learn":[2.185364335e-05],"iteration":515,"passed_time":1.74163887,"remaining_time":1.633630258},
{"learn":[2.101842783e-05],"iteration":516,"passed_time":1.743272091,"remaining_time":1.628627504},
{"learn":[2.047875871e-05],"iteration":517,"passed_time":1.744837035,"remaining_time":1.623574229},
{"learn":[1.97124292e-05],"iteration":518,"passed_time":1.747167426,"remaining_time":1.6192438},
{"learn":[1.90424498e-05],"iteration":519,"passed_time":1.748783311,"remaining_time":1.614261518},
{"learn":[1.855615894e-05],"iteration":520,"passed_time":1.752368029,"remaining_time":1.611102276},
{"learn":[1.788241013e-05],"iteration":521,"passed_time":1.754458801,"remaining_time":1.606573385},
{"learn":[1.729268834e-05],"iteration":522,"passed_time":1.756046024,"remaining_time":1.601594557},
{"learn":[1.685593258e-05],"iteration":523,"passed_time":1.75759949,"remaining_time":1.59659801},
{"learn":[1.649887575e-05],"iteration":524,"passed_time":1.760491406,"remaining_time":1.592825558},
{"learn":[1.613616601e-05],"iteration":525,"passed_time":1.768067402,"remaining_time":1.593277469},
{"learn":[1.569250103e-05],"iteration":526,"passed_time":1.771527682,"remaining_time":1.590004921},
{"learn":[1.533428039e-05],"iteration":527,"passed_time":1.773387457,"remaining_time":1.585300909},
{"learn":[1.499054842e-05],"iteration":528,"passed_time":1.777403012,"remaining_time":1.582527067},
{"learn":[1.465301631e-05],"iteration":529,"passed_time":1.77961865,"remaining_time":1.578152388},
{"learn":[1.421005612e-05],"iteration":530,"passed_time":1.781450516,"remaining_time":1.573446877},
{"learn":[1.370683978e-05],"iteration":531,"passed_time":1.785038778,"remaining_time":1.570297271},
{"learn":[1.343536942e-05],"iteration":532,"passed_time":1.790260709,"remaining_time":1.568577394},
{"learn":[1.3041449e-05],"iteration":533,"passed_time":1.792073334,"remaining_time":1.563869239},
{"learn":[1.26678601e-05],"iteration":534,"passed_time":1.793582538,"remaining_time":1.558908187},
{"learn":[1.236718299e-05],"iteration":535,"passed_time":1.795188815,"remaining_time":1.554044049},
{"learn":[1.192125378e-05],"iteration":536,"passed_time":1.797387723,"remaining_time":1.549703009},
{"learn":[1.161823868e-05],"iteration":537,"passed_time":1.799062749,"remaining_time":1.544920055},
{"learn":[1.135087149e-05],"iteration":538,"passed_time":1.801200649,"remaining_time":1.540544526},
{"learn":[1.103897082e-05],"iteration":539,"passed_time":1.803305156,"remaining_time":1.536148837},
{"learn":[1.077925858e-05],"iteration":540,"passed_time":1.804990883,"remaining_time":1.531406313},
{"learn":[1.055166727e-05],"iteration":541,"passed_time":1.808254969,"remaining_time":1.528008811},
{"learn":[1.033427871e-05],"iteration":542,"passed_time":1.814087494,"remaining_time":1.526773452},
{"learn":[1.012663333e-05],"iteration":543,"passed_time":1.815754156,"remaining_time":1.522029219},
{"learn":[9.816368252e-06],"iteration":544,"passed_time":1.817418311,"remaining_time":1.517294186},
{"learn":[9.569867042e-06],"iteration":545,"passed_time":1.820082463,"remaining_time":1.513401902},
{"learn":[9.293263213e-06],"iteration":546,"passed_time":1.821700156,"remaining_time":1.508647478},
{"learn":[9.052721017e-06],"iteration":547,"passed_time":1.826096785,"remaining_time":1.506196618},
{"learn":[8.762792301e-06],"iteration":548,"passed_time":1.827847009,"remaining_time":1.501564665},
{"learn":[8.489431217e-06],"iteration":549,"passed_time":1.829569492,"remaining_time":1.496920494},
{"learn":[8.274719356e-06],"iteration":550,"passed_time":1.831902314,"remaining_time":1.492784281},
{"learn":[8.005460017e-06],"iteration":551,"passed_time":1.833676492,"remaining_time":1.488201211},
{"learn":[7.763761613e-06],"iteration":552,"passed_time":1.836521367,"remaining_time":1.484493763},
{"learn":[7.598623013e-06],"iteration":553,"passed_time":1.838336792,"remaining_time":1.479960667},
{"learn":[7.449582251e-06],"iteration":554,"passed_time":1.840047838,"remaining_time":1.475353672},
{"learn":[7.284342316e-06],"iteration":555,"passed_time":1.842956145,"remaining_time":1.47171318},
{"learn":[7.146768433e-06],"iteration":556,"passed_time":1.844755926,"remaining_time":1.467193672},
{"learn":[6.959886711e-06],"iteration":557,"passed_time":1.851589892,"remaining_time":1.466671564},
{"learn":[6.774606509e-06],"iteration":558,"passed_time":1.853898657,"remaining_time":1.462556901},
{"learn":[6.617192021e-06],"iteration":559,"passed_time":1.855968027,"remaining_time":1.458260592},
{"learn":[6.448106663e-06],"iteration":560,"passed_time":1.858493886,"remaining_time":1.454329441},
{"learn":[6.270298315e-06],"iteration":561,"passed_time":1.860458432,"remaining_time":1.449965824},
{"learn":[6.130997461e-06],"iteration":562,"passed_time":1.864466541,"remaining_time":1.447196942},
{"learn":[6.02926198e-06],"iteration":563,"passed_time":1.866614252,"remaining_time":1.442985485},
{"learn":[5.898591877e-06],"iteration":564,"passed_time":1.868358853,"remaining_time":1.438470975},
{"learn":[5.800116057e-06],"iteration":565,"passed_time":1.872998841,"remaining_time":1.43618639},
{"learn":[5.676646646e-06],"iteration":566,"passed_time":1.87905358,"remaining_time":1.434973898},
{"learn":[5.583577831e-06],"iteration":567,"passed_time":1.883307037,"remaining_time":1.432374366},
{"learn":[5.451825862e-06],"iteration":568,"passed_time":1.887268615,"remaining_time":1.429547931},
{"learn":[5.311554846e-06],"iteration":569,"passed_time":1.888985552,"remaining_time":1.425024188},
{"learn":[5.200630127e-06],"iteration":570,"passed_time":1.890773919,"remaining_time":1.420563943},
{"learn":[5.074572236e-06],"iteration":571,"passed_time":1.893440894,"remaining_time":1.416770459},
{"learn":[4.937328093e-06],"iteration":572,"passed_time":1.9016816,"remaining_time":1.417134456},
{"learn":[4.816615428e-06],"iteration":573,"passed_time":1.903544494,"remaining_time":1.412735112},
{"learn":[4.665321121e-06],"iteration":574,"passed_time":1.905292775,"remaining_time":1.408259877},
{"learn":[4.547202802e-06],"iteration":575,"passed_time":1.907932413,"remaining_time":1.404450249},
{"learn":[4.397942263e-06],"iteration":576,"passed_time":1.909782387,"remaining_time":1.40006577},
{"learn":[4.277888023e-06],"iteration":577,"passed_time":1.914273931,"remaining_time":1.397618683},
{"learn":[4.135835259e-06],"iteration":578,"passed_time":1.916043937,"remaining_time":1.39318566},
{"learn":[4.024014038e-06],"iteration":579,"passed_time":1.918234958,"remaining_time":1.389066694},
{"learn":[3.926733644e-06],"iteration":580,"passed_time":1.920330461,"remaining_time":1.384885478},
{"learn":[3.806498987e-06],"iteration":581,"passed_time":1.923651435,"remaining_time":1.38159158},
{"learn":[3.737890263e-06],"iteration":582,"passed_time":1.925785242,"remaining_time":1.37744845},
{"learn":[3.638241663e-06],"iteration":583,"passed_time":1.927485141,"remaining_time":1.373003114},
{"learn":[3.542506397e-06],"iteration":584,"passed_time":1.929153554,"remaining_time":1.368544829},
{"learn":[3.458906632e-06],"iteration":585,"passed_time":1.931315327,"remaining_time":1.364444617},
{"learn":[3.379256491e-06],"iteration":586,"passed_time":1.934232732,"remaining_time":1.360882655},
{"learn":[3.319436063e-06],"iteration":587,"passed_time":1.936982342,"remaining_time":1.357205315},
{"learn":[3.249140908e-06],"iteration":588,"passed_time":1.939016798,"remaining_time":1.353032095},
{"learn":[3.176229161e-06],"iteration":589,"passed_time":1.940746548,"remaining_time":1.348654381},
{"learn":[3.115705535e-06],"iteration":590,"passed_time":1.949859305,"remaining_time":1.349395018},
{"learn":[3.061761823e-06],"iteration":591,"passed_time":1.951496905,"remaining_time":1.34495057},
{"learn":[3.005453755e-06],"iteration":592,"passed_time":1.953721288,"remaining_time":1.340918321},
{"learn":[2.942769836e-06],"iteration":593,"passed_time":1.955806607,"remaining_time":1.336797108},
{"learn":[2.877976442e-06],"iteration":594,"passed_time":1.957583304,"remaining_time":1.332472669},
{"learn":[2.826191893e-06],"iteration":595,"passed_time":1.962813167,"remaining_time":1.330497516},
{"learn":[2.779148916e-06],"iteration":596,"passed_time":1.964825329,"remaining_time":1.326339376},
{"learn":[2.721821981e-06],"iteration":597,"passed_time":1.966491873,"remaining_time":1.321956075},
{"learn":[2.663296977e-06],"iteration":598,"passed_time":1.968079546,"remaining_time":1.317529045},
{"learn":[2.588406826e-06],"iteration":599,"passed_time":1.971310014,"remaining_time":1.314206676},
{"learn":[2.544707829e-06],"iteration":600,"passed_time":1.97368719,"remaining_time":1.310318118},
{"learn":[2.50284515e-06],"iteration":601,"passed_time":1.976319829,"remaining_time":1.306603475},
{"learn":[2.462521113e-06],"iteration":602,"passed_time":1.978247248,"remaining_time":1.302428122},
{"learn":[2.383836134e-06],"iteration":603,"passed_time":1.97994437,"remaining_time":1.298109222},
{"learn":[2.330981009e-06],"iteration":604,"passed_time":1.982133468,"remaining_time":1.294120198},
{"learn":[2.261991644e-06],"iteration":605,"passed_time":1.984722627,"remaining_time":1.290397219},
{"learn":[2.214443042e-06],"iteration":606,"passed_time":1.987828622,"remaining_time":1.2870126},
{"learn":[2.139307595e-06],"iteration":607,"passed_time":1.98993667,"remaining_time":1.282985485},
{"learn":[2.071673763e-06],"iteration":608,"passed_time":1.991543834,"remaining_time":1.278643085},
{"learn":[2.037658983e-06],"iteration":609,"passed_time":1.993338012,"remaining_time":1.274429221},
{"learn":[2.005080477e-06],"iteration":610,"passed_time":1.998185186,"remaining_time":1.272167001},
{"learn":[1.944384158e-06],"iteration":611,"passed_time":2.009442321,"remaining_time":1.273960164},
{"learn":[1.897689331e-06],"iteration":612,"passed_time":2.010917086,"remaining_time":1.26953493},
{"learn":[1.839777018e-06],"iteration":613,"passed_time":2.012729568,"remaining_time":1.265331618},
{"learn":[1.788635056e-06],"iteration":614,"passed_time":2.016400903,"remaining_time":1.262299752},
{"learn":[1.739418451e-06],"iteration":615,"passed_time":2.020858896,"remaining_time":1.259756195},
{"learn":[1.695190108e-06],"iteration":616,"passed_time":2.022400343,"remaining_time":1.255395999},
{"learn":[1.660796158e-06],"iteration":617,"passed_time":2.023910662,"remaining_time":1.251025684},
{"learn":[1.627456444e-06],"iteration":618,"passed_time":2.025717623,"remaining_time":1.246847196},
{"learn":[1.582713526e-06],"iteration":619,"passed_time":2.029144275,"remaining_time":1.243669072},
{"learn":[1.539647188e-06],"iteration":620,"passed_time":2.031250093,"remaining_time":1.239684034},
{"learn":[1.490456868e-06],"iteration":621,"passed_time":2.032791734,"remaining_time":1.235362179},
{"learn":[1.464970208e-06],"iteration":622,"passed_time":2.035932973,"remaining_time":1.232017224},
{"learn":[1.410305846e-06],"iteration":623,"passed_time":2.037685595,"remaining_time":1.227836192},
{"learn":[1.377696077e-06],"iteration":624,"passed_time":2.041281113,"remaining_time":1.224768668},
{"learn":[1.338726322e-06],"iteration":625,"passed_time":2.046567206,"remaining_time":1.222709481},
{"learn":[1.311608746e-06],"iteration":626,"passed_time":2.048099458,"remaining_time":1.218406855},
{"learn":[1.285650599e-06],"iteration":627,"passed_time":2.049900895,"remaining_time":1.214272504},
{"learn":[1.256986921e-06],"iteration":628,"passed_time":2.051414985,"remaining_time":1.209976088},
{"learn":[1.232817594e-06],"iteration":629,"passed_time":2.057151486,"remaining_time":1.208168333},
{"learn":[1.20890776e-06],"iteration":630,"passed_time":2.058704805,"remaining_time":1.203901859},
{"learn":[1.168467142e-06],"iteration":631,"passed_time":2.060478956,"remaining_time":1.199772557},
{"learn":[1.135688785e-06],"iteration":632,"passed_time":2.062464431,"remaining_time":1.195773217},
{"learn":[1.117673953e-06],"iteration":633,"passed_time":2.063953503,"remaining_time":1.191493663},
{"learn":[1.090521631e-06],"iteration":634,"passed_time":2.065576317,"remaining_time":1.187299773},
{"learn":[1.057517673e-06],"iteration":635,"passed_time":2.068194626,"remaining_time":1.183683717},
{"learn":[1.030211942e-06],"iteration":636,"passed_time":2.069777767,"remaining_time":1.179480894},
{"learn":[1.002187898e-06],"iteration":637,"passed_time":2.072057669,"remaining_time":1.175681624},
{"learn":[9.756117097e-07],"iteration":638,"passed_time":2.073956203,"remaining_time":1.171671658},
{"learn":[9.6010249e-07],"iteration":639,"passed_time":2.076780785,"remaining_time":1.168189192},
{"learn":[9.359658107e-07],"iteration":640,"passed_time":2.079207721,"remaining_time":1.164486071},
{"learn":[9.214936153e-07],"iteration":641,"passed_time":2.080802574,"remaining_time":1.160322931},
{"learn":[8.970064803e-07],"iteration":642,"passed_time":2.085364374,"remaining_time":1.157815057},
{"learn":[8.715863765e-07],"iteration":643,"passed_time":2.086978864,"remaining_time":1.153671546},
{"learn":[8.507754231e-07],"iteration":644,"passed_time":2.093398984,"remaining_time":1.152180836},
{"learn":[8.310576476e-07],"iteration":645,"passed_time":2.097461393,"remaining_time":1.149382869},
{"learn":[8.063582164e-07],"iteration":646,"passed_time":2.101226105,"remaining_time":1.14641857},
{"learn":[7.881646886e-07],"iteration":647,"passed_time":2.106346026,"remaining_time":1.144187965},
{"learn":[7.627118879e-07],"iteration":648,"passed_time":2.108574921,"remaining_time":1.140384896},
{"learn":[7.385865809e-07],"iteration":649,"passed_time":2.110252447,"remaining_time":1.136289779},
{"learn":[7.156794273e-07],"iteration":650,"passed_time":2.112259356,"remaining_time":1.132378672},
{"learn":[6.953519262e-07],"iteration":651,"passed_time":2.11583643,"remaining_time":1.129311469},
{"learn":[6.744339666e-07],"iteration":652,"passed_time":2.119294186,"remaining_time":1.126179299},
{"learn":[6.666930585e-07],"iteration":653,"passed_time":2.121847569,"remaining_time":1.122567674},
{"learn":[6.487091307e-07],"iteration":654,"passed_time":2.123731149,"remaining_time":1.118606483},
{"learn":[6.277541616e-07],"iteration":655,"passed_time":2.129598026,"remaining_time":1.116740428},
{"learn":[6.040280355e-07],"iteration":656,"passed_time":2.131420284,"remaining_time":1.11275062},
{"learn":[5.839901104e-07],"iteration":657,"passed_time":2.134245908,"remaining_time":1.109288907},
{"learn":[5.738527503e-07],"iteration":658,"passed_time":2.14079272,"remaining_time":1.107754655},
{"learn":[5.641823068e-07],"iteration":659,"passed_time":2.145104409,"remaining_time":1.105053787},
{"learn":[5.50534584e-07],"iteration":660,"passed_time":2.147400958,"remaining_time":1.101314561},
{"learn":[5.343384097e-07],"iteration":661,"passed_time":2.154872342,"remaining_time":1.10022183},
{"learn":[5.188642626e-07],"iteration":662,"passed_time":2.168200086,"remaining_time":1.10208662},
{"learn":[5.041522263e-07],"iteration":663,"passed_time":2.169860522,"remaining_time":1.09800171},
{"learn":[4.871986402e-07],"iteration":664,"passed_time":2.175057416,"remaining_time":1.095705616},
{"learn":[4.736289099e-07],"iteration":665,"passed_time":2.177261337,"remaining_time":1.09189983},
{"learn":[4.61165863e-07],"iteration":666,"passed_time":2.179551395,"remaining_time":1.088141851},
{"learn":[4.55426286e-07],"iteration":667,"passed_time":2.181140549,"remaining_time":1.084039914},
{"learn":[4.459347281e-07],"iteration":668,"passed_time":2.184360452,"remaining_time":1.080752331},
{"learn":[4.327668404e-07],"iteration":669,"passed_time":2.186184068,"remaining_time":1.076777228},
{"learn":[4.201400071e-07],"iteration":670,"passed_time":2.188371414,"remaining_time":1.072986878},
{"learn":[4.080327554e-07],"iteration":671,"passed_time":2.190340734,"remaining_time":1.069094882},
{"learn":[3.991065034e-07],"iteration":672,"passed_time":2.191844075,"remaining_time":1.064982188},
{"learn":[3.86837867e-07],"iteration":673,"passed_time":2.193413386,"remaining_time":1.060909145},
{"learn":[3.774071191e-07],"iteration":674,"passed_time":2.195498289,"remaining_time":1.057091769},
{"learn":[3.659424971e-07],"iteration":675,"passed_time":2.19802192,"remaining_time":1.053489796},
{"learn":[3.568206365e-07],"iteration":676,"passed_time":2.200048173,"remaining_time":1.049653707},
{"learn":[3.452314562e-07],"iteration":677,"passed_time":2.201602393,"remaining_time":1.045598777},
{"learn":[3.351579317e-07],"iteration":678,"passed_time":2.205705096,"remaining_time":1.042756017},
{"learn":[3.261812682e-07],"iteration":679,"passed_time":2.208574165,"remaining_time":1.039329019},
{"learn":[3.225638712e-07],"iteration":680,"passed_time":2.210722969,"remaining_time":1.035566266},
{"learn":[3.143534935e-07],"iteration":681,"passed_time":2.213449685,"remaining_time":1.032077712},
{"learn":[3.064843586e-07],"iteration":682,"passed_time":2.215145613,"remaining_time":1.028112971},
{"learn":[2.977251874e-07],"iteration":683,"passed_time":2.21677472,"remaining_time":1.024123994},
{"learn":[2.903541162e-07],"iteration":684,"passed_time":2.218655215,"remaining_time":1.020257508},
{"learn":[2.840128037e-07],"iteration":685,"passed_time":2.220170782,"remaining_time":1.016229775},
{"learn":[2.770618571e-07],"iteration":686,"passed_time":2.221671303,"remaining_time":1.0122025},
{"learn":[2.705702172e-07],"iteration":687,"passed_time":2.224537799,"remaining_time":1.008802025},
{"learn":[2.626177636e-07],"iteration":688,"passed_time":2.226101862,"remaining_time":1.004815209},
{"learn":[2.546446611e-07],"iteration":689,"passed_time":2.22780126,"remaining_time":1.000896218},
{"learn":[2.470049031e-07],"iteration":690,"passed_time":2.230927001,"remaining_time":0.9976214809},
{"learn":[2.396850328e-07],"iteration":691,"passed_time":2.235691444,"remaining_time":0.9950765385},
{"learn":[2.326721703e-07],"iteration":692,"passed_time":2.237377948,"remaining_time":0.9911616595},
{"learn":[2.26324116e-07],"iteration":693,"passed_time":2.239119445,"remaining_time":0.98727745},
{"learn":[2.202280988e-07],"iteration":694,"passed_time":2.241790179,"remaining_time":0.983807201},
{"learn":[2.143741901e-07],"iteration":695,"passed_time":2.243700843,"remaining_time":0.9800072648},
{"learn":[2.087528938e-07],"iteration":696,"passed_time":2.24551013,"remaining_time":0.9761686791},
{"learn":[2.03355129e-07],"iteration":697,"passed_time":2.247827095,"remaining_time":0.9725555624},
{"learn":[1.982729802e-07],"iteration":698,"passed_time":2.249338251,"remaining_time":0.9685991611},
{"learn":[1.933548268e-07],"iteration":699,"passed_time":2.251000159,"remaining_time":0.964714354},
{"learn":[1.885954579e-07],"iteration":700,"passed_time":2.25554515,"remaining_time":0.9620656205},
{"learn":[1.839898586e-07],"iteration":701,"passed_time":2.25725781,"remaining_time":0.9582091557},
{"learn":[1.795332019e-07],"iteration":702,"passed_time":2.258915906,"remaining_time":0.9543357383},
{"learn":[1.752208362e-07],"iteration":703,"passed_time":2.26200199,"remaining_time":0.9510690185},
{"learn":[1.710482829e-07],"iteration":704,"passed_time":2.264953903,"remaining_time":0.9477466687},
{"learn":[1.670112233e-07],"iteration":705,"passed_time":2.270612076,"remaining_time":0.9455523378},
{"learn":[1.631054963e-07],"iteration":706,"passed_time":2.273364493,"remaining_time":0.9421439835},
{"learn":[1.593270896e-07],"iteration":707,"passed_time":2.278765857,"remaining_time":0.9398299863},
{"learn":[1.555080928e-07],"iteration":708,"passed_time":2.281166347,"remaining_time":0.9362756091},
{"learn":[1.513669699e-07],"iteration":709,"passed_time":2.282954459,"remaining_time":0.9324743566},
{"learn":[1.469264738e-07],"iteration":710,"passed_time":2.285600306,"remaining_time":0.9290274097},
{"learn":[1.419385005e-07],"iteration":711,"passed_time":2.288443637,"remaining_time":0.9256625949},
{"learn":[1.375736505e-07],"iteration":712,"passed_time":2.290002485,"remaining_time":0.9217822064},
{"learn":[1.334482201e-07],"iteration":713,"passed_time":2.292237842,"remaining_time":0.9181793038},
{"learn":[1.293778128e-07],"iteration":714,"passed_time":2.2990247,"remaining_time":0.9163944608},
{"learn":[1.251313249e-07],"iteration":715,"passed_time":2.30067645,"remaining_time":0.9125588155},
{"learn":[1.21430014e-07],"iteration":716,"passed_time":2.303146734,"remaining_time":0.9090523373},
{"learn":[1.176195813e-07],"iteration":717,"passed_time":2.305038717,"remaining_time":0.9053216131},
{"learn":[1.151005647e-07],"iteration":718,"passed_time":2.308493604,"remaining_time":0.9022068189},
{"learn":[1.123174886e-07],"iteration":719,"passed_time":2.311060653,"remaining_time":0.8987458097},
{"learn":[1.099507487e-07],"iteration":720,"passed_time":2.312854886,"remaining_time":0.8949882293},
{"learn":[1.067397395e-07],"iteration":721,"passed_time":2.314472013,"remaining_time":0.8911678943},
{"learn":[1.038901066e-07],"iteration":722,"passed_time":2.32142147,"remaining_time":0.8893966074},
{"learn":[1.016388305e-07],"iteration":723,"passed_time":2.323336464,"remaining_time":0.8856918012},
{"learn":[9.910516464e-08],"iteration":724,"passed_time":2.326850165,"remaining_time":0.8825983383},
{"learn":[9.608577402e-08],"iteration":725,"passed_time":2.328629208,"remaining_time":0.8788490399},
{"learn":[9.411140429e-08],"iteration":726,"passed_time":2.330501141,"remaining_time":0.8751400431},
{"learn":[9.204300592e-08],"iteration":727,"passed_time":2.33592337,"remaining_time":0.8727625778},
{"learn":[8.936249727e-08],"iteration":728,"passed_time":2.339124938,"remaining_time":0.8695512457},
{"learn":[8.707994494e-08],"iteration":729,"passed_time":2.340656963,"remaining_time":0.8657224386},
{"learn":[8.488763246e-08],"iteration":730,"passed_time":2.3437694,"remaining_time":0.8624814893},
{"learn":[8.386681704e-08],"iteration":731,"passed_time":2.346108576,"remaining_time":0.8589577845},
{"learn":[8.174145192e-08],"iteration":732,"passed_time":2.347656545,"remaining_time":0.8551491097},
{"learn":[7.874171526e-08],"iteration":733,"passed_time":2.349187338,"remaining_time":0.8513403703},
{"learn":[7.64866246e-08],"iteration":734,"passed_time":2.350825887,"remaining_time":0.8475766802},
{"learn":[7.453806182e-08],"iteration":735,"passed_time":2.354670564,"remaining_time":0.8446100937},
{"learn":[7.369596785e-08],"iteration":736,"passed_time":2.356181506,"remaining_time":0.8408083256},
{"learn":[7.291205582e-08],"iteration":737,"passed_time":2.358791218,"remaining_time":0.8374028444},
{"learn":[7.097144183e-08],"iteration":738,"passed_time":2.361173441,"remaining_time":0.8339191722},
{"learn":[6.925402536e-08],"iteration":739,"passed_time":2.362879202,"remaining_time":0.8302008007},
{"learn":[6.748357078e-08],"iteration":740,"passed_time":2.367829795,"remaining_time":0.82762202},
{"learn":[6.578262925e-08],"iteration":741,"passed_time":2.36936763,"remaining_time":0.8238502},
{"learn":[6.414861718e-08],"iteration":742,"passed_time":2.371198414,"remaining_time":0.8201857233},
{"learn":[6.257905465e-08],"iteration":743,"passed_time":2.372871114,"remaining_time":0.8164717811},
{"learn":[6.143940101e-08],"iteration":744,"passed_time":2.382659877,"remaining_time":0.8155413002},
{"learn":[5.959006502e-08],"iteration":745,"passed_time":2.384347814,"remaining_time":0.8118288804},
{"learn":[5.806493886e-08],"iteration":746,"passed_time":2.386235726,"remaining_time":0.8081896101},
{"learn":[5.726899269e-08],"iteration":747,"passed_time":2.39007139,"remaining_time":0.8052112168},
{"learn":[5.654042978e-08],"iteration":748,"passed_time":2.392040777,"remaining_time":0.8016051202},
{"learn":[5.592194669e-08],"iteration":749,"passed_time":2.394325648,"remaining_time":0.7981085492},
{"learn":[5.453483958e-08],"iteration":750,"passed_time":2.396042588,"remaining_time":0.7944269033},
{"learn":[5.320227773e-08],"iteration":751,"passed_time":2.415454153,"remaining_time":0.796585944},
{"learn":[5.172694142e-08],"iteration":752,"passed_time":2.418479173,"remaining_time":0.7933125574},
{"learn":[5.009017998e-08],"iteration":753,"passed_time":2.421689723,"remaining_time":0.7901003607},
{"learn":[4.872863239e-08],"iteration":754,"passed_time":2.423889046,"remaining_time":0.7865600214},
{"learn":[4.776548535e-08],"iteration":755,"passed_time":2.425852524,"remaining_time":0.7829471108},
{"learn":[4.671169174e-08],"iteration":756,"passed_time":2.427428784,"remaining_time":0.7792142596},
{"learn":[4.551368277e-08],"iteration":757,"passed_time":2.429098158,"remaining_time":0.7755168263},
{"learn":[4.441540897e-08],"iteration":758,"passed_time":2.431184084,"remaining_time":0.7719570015},
{"learn":[4.329638488e-08],"iteration":759,"passed_time":2.435590631,"remaining_time":0.7691338836},
{"learn":[4.185844208e-08],"iteration":760,"passed_time":2.43746902,"remaining_time":0.7655126095},
{"learn":[4.071526292e-08],"iteration":761,"passed_time":2.439316157,"remaining_time":0.7618861489},
{"learn":[3.971593956e-08],"iteration":762,"passed_time":2.440928922,"remaining_time":0.7581915525},
{"learn":[3.877215995e-08],"iteration":763,"passed_time":2.442893604,"remaining_time":0.7546111134},
{"learn":[3.749471329e-08],"iteration":764,"passed_time":2.446143687,"remaining_time":0.7514297601},
{"learn":[3.661256835e-08],"iteration":765,"passed_time":2.448637402,"remaining_time":0.7480171699},
{"learn":[3.541858017e-08],"iteration":766,"passed_time":2.450583678,"remaining_time":0.744440674},
{"learn":[3.428152113e-08],"iteration":767,"passed_time":2.452199786,"remaining_time":0.7407686852},
{"learn":[3.335484124e-08],"iteration":768,"passed_time":2.453713325,"remaining_time":0.7370712329},
{"learn":[3.257683489e-08],"iteration":769,"passed_time":2.455586829,"remaining_time":0.7334869749},
{"learn":[3.177910986e-08],"iteration":770,"passed_time":2.460915956,"remaining_time":0.7309335328},
{"learn":[3.120952095e-08],"iteration":771,"passed_time":2.462670333,"remaining_time":0.727317145},
{"learn":[3.023023671e-08],"iteration":772,"passed_time":2.464823211,"remaining_time":0.7238225988},
{"learn":[2.952814456e-08],"iteration":773,"passed_time":2.467116089,"remaining_time":0.720372398},
{"learn":[2.862032147e-08],"iteration":774,"passed_time":2.472026315,"remaining_time":0.7176850591},
{"learn":[2.775883936e-08],"iteration":775,"passed_time":2.47678864,"remaining_time":0.7149492981},
{"learn":[2.712048453e-08],"iteration":776,"passed_time":2.482241103,"remaining_time":0.7124063913},
{"learn":[2.63211499e-08],"iteration":777,"passed_time":2.48496174,"remaining_time":0.7090764861},
{"learn":[2.538996534e-08],"iteration":778,"passed_time":2.48668234,"remaining_time":0.705464438},
{"learn":[2.474263426e-08],"iteration":779,"passed_time":2.48873462,"remaining_time":0.7019507903},
{"learn":[2.406002885e-08],"iteration":780,"passed_time":2.490196961,"remaining_time":0.6982754604},
{"learn":[2.336214755e-08],"iteration":781,"passed_time":2.491900496,"remaining_time":0.6946730283},
{"learn":[2.269447627e-08],"iteration":782,"passed_time":2.495692729,"remaining_time":0.6916543068},
{"learn":[2.208827873e-08],"iteration":783,"passed_time":2.501372033,"remaining_time":0.6891535194},
{"learn":[2.151544667e-08],"iteration":784,"passed_time":2.503037673,"remaining_time":0.68554535},
{"learn":[2.078258435e-08],"iteration":785,"passed_time":2.506059852,"remaining_time":0.682311461},
{"learn":[2.025566516e-08],"iteration":786,"passed_time":2.507844394,"remaining_time":0.6787431459},
{"learn":[1.964984392e-08],"iteration":787,"passed_time":2.512816472,"remaining_time":0.6760369189},
{"learn":[1.909046813e-08],"iteration":788,"passed_time":2.519768719,"remaining_time":0.673854499},
{"learn":[1.862576724e-08],"iteration":789,"passed_time":2.522003315,"remaining_time":0.6704059444},
{"learn":[1.808550062e-08],"iteration":790,"passed_time":2.523661973,"remaining_time":0.6668082835},
{"learn":[1.787015756e-08],"iteration":791,"passed_time":2.52544735,"remaining_time":0.663248799},
{"learn":[1.727122679e-08],"iteration":792,"passed_time":2.530761652,"remaining_time":0.6606149583},
{"learn":[1.668724718e-08],"iteration":793,"passed_time":2.537351926,"remaining_time":0.6583054114},
{"learn":[1.648721607e-08],"iteration":794,"passed_time":2.546487822,"remaining_time":0.6566415138},
{"learn":[1.629875331e-08],"iteration":795,"passed_time":2.549531317,"remaining_time":0.6533974732},
{"learn":[1.578059971e-08],"iteration":796,"passed_time":2.551280618,"remaining_time":0.6498242979},
{"learn":[1.561066897e-08],"iteration":797,"passed_time":2.554217511,"remaining_time":0.6465563122},
{"learn":[1.54444487e-08],"iteration":798,"passed_time":2.558178782,"remaining_time":0.6435468524},
{"learn":[1.494419979e-08],"iteration":799,"passed_time":2.559742945,"remaining_time":0.6399357362},
{"learn":[1.458753254e-08],"iteration":800,"passed_time":2.56604548,"remaining_time":0.6375069294},
{"learn":[1.44535944e-08],"iteration":801,"passed_time":2.567491358,"remaining_time":0.6338694375},
{"learn":[1.421386242e-08],"iteration":802,"passed_time":2.569779953,"remaining_time":0.6304441478},
{"learn":[1.392305897e-08],"iteration":803,"passed_time":2.571260241,"remaining_time":0.6268246359},
{"learn":[1.352707722e-08],"iteration":804,"passed_time":2.572833831,"remaining_time":0.6232330398},
{"learn":[1.311230244e-08],"iteration":805,"passed_time":2.574373025,"remaining_time":0.6196381724},
{"learn":[1.290294041e-08],"iteration":806,"passed_time":2.576356475,"remaining_time":0.6161546464},
{"learn":[1.270461635e-08],"iteration":807,"passed_time":2.577945855,"remaining_time":0.6125811932},
{"learn":[1.237945195e-08],"iteration":808,"passed_time":2.580374834,"remaining_time":0.6092108692},
{"learn":[1.204228989e-08],"iteration":809,"passed_time":2.582457952,"remaining_time":0.6057617419},
{"learn":[1.181222316e-08],"iteration":810,"passed_time":2.584677406,"remaining_time":0.6023477556},
{"learn":[1.159353788e-08],"iteration":811,"passed_time":2.585918553,"remaining_time":0.5987102068},
{"learn":[1.140250754e-08],"iteration":812,"passed_time":2.590164311,"remaining_time":0.5957696509},
{"learn":[1.11172242e-08],"iteration":813,"passed_time":2.592143947,"remaining_time":0.5923080762},
{"learn":[1.101000932e-08],"iteration":814,"passed_time":2.593751349,"remaining_time":0.5887656436},
{"learn":[1.068335662e-08],"iteration":815,"passed_time":2.596599053,"remaining_time":0.5855076296},
{"learn":[1.041310642e-08],"iteration":816,"passed_time":2.598235581,"remaining_time":0.5819793284},
{"learn":[1.032893051e-08],"iteration":817,"passed_time":2.604203137,"remaining_time":0.5794192799},
{"learn":[1.021900781e-08],"iteration":818,"passed_time":2.606489847,"remaining_time":0.5760374387},
{"learn":[9.955185035e-09],"iteration":819,"passed_time":2.608256846,"remaining_time":0.5725441856},
{"learn":[9.73015404e-09],"iteration":820,"passed_time":2.609899941,"remaining_time":0.5690281236},
{"learn":[9.533577921e-09],"iteration":821,"passed_time":2.611700394,"remaining_time":0.5655506935},
{"learn":[9.260366262e-09],"iteration":822,"passed_time":2.61504119,"remaining_time":0.5624086155},
{"learn":[9.032843578e-09],"iteration":823,"passed_time":2.618646595,"remaining_time":0.5593225737},
{"learn":[8.885191431e-09],"iteration":824,"passed_time":2.620456451,"remaining_time":0.5558543987},
{"learn":[8.817926158e-09],"iteration":825,"passed_time":2.621952217,"remaining_time":0.5523240748},
{"learn":[8.570208438e-09],"iteration":826,"passed_time":2.623860808,"remaining_time":0.54888503},
{"learn":[8.332175197e-09],"iteration":827,"passed_time":2.627736599,"remaining_time":0.5458583272},
{"learn":[8.145127681e-09],"iteration":828,"passed_time":2.63173594,"remaining_time":0.5428550613},
{"learn":[8.062749679e-09],"iteration":829,"passed_time":2.637714781,"remaining_time":0.5402548346},
{"learn":[7.8600462e-09],"iteration":830,"passed_time":2.640122531,"remaining_time":0.5369202259},
{"learn":[7.614850622e-09],"iteration":831,"passed_time":2.643284506,"remaining_time":0.5337401407},
{"learn":[7.383283614e-09],"iteration":832,"passed_time":2.648504435,"remaining_time":0.5309726779},
{"learn":[7.31218848e-09],"iteration":833,"passed_time":2.651880587,"remaining_time":0.527832347},
{"learn":[7.138970998e-09],"iteration":834,"passed_time":2.653686128,"remaining_time":0.5243810911},
{"learn":[7.009081313e-09],"iteration":835,"passed_time":2.65569019,"remaining_time":0.5209727167},
{"learn":[6.817091031e-09],"iteration":836,"passed_time":2.657285261,"remaining_time":0.5174880495},
{"learn":[6.645756621e-09],"iteration":837,"passed_time":2.660222091,"remaining_time":0.5142672778},
{"learn":[6.448568808e-09],"iteration":838,"passed_time":2.662356057,"remaining_time":0.510893117},
{"learn":[6.285066972e-09],"iteration":839,"passed_time":2.667275901,"remaining_time":0.5080525527},
{"learn":[6.129745863e-09],"iteration":840,"passed_time":2.676700788,"remaining_time":0.5060587697},
{"learn":[5.951942134e-09],"iteration":841,"passed_time":2.678428597,"remaining_time":0.5026029909},
{"learn":[5.820832008e-09],"iteration":842,"passed_time":2.682405156,"remaining_time":0.499570118},
{"learn":[5.706852756e-09],"iteration":843,"passed_time":2.692611439,"remaining_time":0.4976864745},
{"learn":[5.550538263e-09],"iteration":844,"passed_time":2.694469432,"remaining_time":0.4942517893},
{"learn":[5.400900683e-09],"iteration":845,"passed_time":2.697426078,"remaining_time":0.4910208227},
{"learn":[5.261317957e-09],"iteration":846,"passed_time":2.699005597,"remaining_time":0.487541743},
{"learn":[5.127616033e-09],"iteration":847,"passed_time":2.70074336,"remaining_time":0.4840955079},
{"learn":[5.007822846e-09],"iteration":848,"passed_time":2.70404032,"remaining_time":0.4809306106},
{"learn":[4.882305108e-09],"iteration":849,"passed_time":2.705747424,"remaining_time":0.4774848395},
{"learn":[4.761786811e-09],"iteration":850,"passed_time":2.719914805,"remaining_time":0.4762248013},
{"learn":[4.663972727e-09],"iteration":851,"passed_time":2.722733245,"remaining_time":0.4729630519},
{"learn":[4.540584181e-09],"iteration":852,"passed_time":2.726595499,"remaining_time":0.4698822255},
{"learn":[4.433482336e-09],"iteration":853,"passed_time":2.729675147,"remaining_time":0.4666657745},
{"learn":[4.333347712e-09],"iteration":854,"passed_time":2.731496657,"remaining_time":0.4632362751},
{"learn":[4.220112096e-09],"iteration":855,"passed_time":2.733853077,"remaining_time":0.4599005177},
{"learn":[4.116218397e-09],"iteration":856,"passed_time":2.735802079,"remaining_time":0.4564990634},
{"learn":[4.010610016e-09],"iteration":857,"passed_time":2.739056306,"remaining_time":0.453317011},
{"learn":[3.912835147e-09],"iteration":858,"passed_time":2.741606307,"remaining_time":0.4500191959},
{"learn":[3.846137023e-09],"iteration":859,"passed_time":2.743503278,"remaining_time":0.4466168126},
{"learn":[3.766399321e-09],"iteration":860,"passed_time":2.745904347,"remaining_time":0.4432993081},
{"learn":[3.675814306e-09],"iteration":861,"passed_time":2.756292013,"remaining_time":0.4412625264},
{"learn":[3.614026983e-09],"iteration":862,"passed_time":2.758442878,"remaining_time":0.4378988114},
{"learn":[3.546649524e-09],"iteration":863,"passed_time":2.760384079,"remaining_time":0.4345049014},
{"learn":[3.462540731e-09],"iteration":864,"passed_time":2.770751473,"remaining_time":0.4324294206},
{"learn":[3.369997548e-09],"iteration":865,"passed_time":2.78369192,"remaining_time":0.4307329299},
{"learn":[3.273283351e-09],"iteration":866,"passed_time":2.786073076,"remaining_time":0.4273906794},
{"learn":[3.180682278e-09],"iteration":867,"passed_time":2.787884044,"remaining_time":0.4239639329},
{"learn":[3.084722451e-09],"iteration":868,"passed_time":2.790948441,"remaining_time":0.4207298571},
{"learn":[2.999364817e-09],"iteration":869,"passed_time":2.792805813,"remaining_time":0.4173158111},
{"learn":[2.9466127e-09],"iteration":870,"passed_time":2.795003736,"remaining_time":0.4139557771},
{"learn":[2.87100214e-09],"iteration":871,"passed_time":2.797296982,"remaining_time":0.410612401},
{"learn":[2.821356217e-09],"iteration":872,"passed_time":2.800732567,"remaining_time":0.4074376128},
{"learn":[2.767641903e-09],"iteration":873,"passed_time":2.808872343,"remaining_time":0.4049404064},
{"learn":[2.7261277e-09],"iteration":874,"passed_time":2.811227893,"remaining_time":0.4016039847},
{"learn":[2.686727532e-09],"iteration":875,"passed_time":2.813214384,"remaining_time":0.3982175611},
{"learn":[2.597084989e-09],"iteration":876,"passed_time":2.815658734,"remaining_time":0.3948985454},
{"learn":[2.530983076e-09],"iteration":877,"passed_time":2.823785485,"remaining_time":0.3923711038},
{"learn":[2.488580171e-09],"iteration":878,"passed_time":2.82658985,"remaining_time":0.3890982615},
{"learn":[2.433985765e-09],"iteration":879,"passed_time":2.831048013,"remaining_time":0.3860520018},
{"learn":[2.362724744e-09],"iteration":880,"passed_time":2.835208167,"remaining_time":0.3829622836},
{"learn":[2.28543355e-09],"iteration":881,"passed_time":2.837537418,"remaining_time":0.3796251875},
{"learn":[2.228122741e-09],"iteration":882,"passed_time":2.844681707,"remaining_time":0.3769283803},
{"learn":[2.173048662e-09],"iteration":883,"passed_time":2.851716146,"remaining_time":0.374207096},
{"learn":[2.134874275e-09],"iteration":884,"passed_time":2.853509585,"remaining_time":0.3707950308},
{"learn":[2.098246367e-09],"iteration":885,"passed_time":2.855221875,"remaining_time":0.367376178},
{"learn":[2.052823492e-09],"iteration":886,"passed_time":2.860153226,"remaining_time":0.3643712677},
{"learn":[2.002379915e-09],"iteration":887,"passed_time":2.861931116,"remaining_time":0.3609642849},
{"learn":[1.956729679e-09],"iteration":888,"passed_time":2.863451448,"remaining_time":0.3575288085},
{"learn":[1.912969586e-09],"iteration":889,"passed_time":2.865276945,"remaining_time":0.3541353528},
{"learn":[1.859226233e-09],"iteration":890,"passed_time":2.871162011,"remaining_time":0.3512420418},
{"learn":[1.814637381e-09],"iteration":891,"passed_time":2.874163025,"remaining_time":0.3479928327},
{"learn":[1.76668052e-09],"iteration":892,"passed_time":2.875874122,"remaining_time":0.3445896204},
{"learn":[1.720660533e-09],"iteration":893,"passed_time":2.878509034,"remaining_time":0.3412997289},
{"learn":[1.679133972e-09],"iteration":894,"passed_time":2.882500316,"remaining_time":0.3381704281},
{"learn":[1.641802232e-09],"iteration":895,"passed_time":2.886070601,"remaining_time":0.3349903376},
{"learn":[1.606169608e-09],"iteration":896,"passed_time":2.892418089,"remaining_time":0.3321282755},
{"learn":[1.565055293e-09],"iteration":897,"passed_time":2.894493715,"remaining_time":0.3287732282},
{"learn":[1.521417342e-09],"iteration":898,"passed_time":2.896206766,"remaining_time":0.325380293},
{"learn":[1.480893222e-09],"iteration":899,"passed_time":2.898113397,"remaining_time":0.3220125996},
{"learn":[1.442432229e-09],"iteration":900,"passed_time":2.902473076,"remaining_time":0.3189176854},
{"learn":[1.412663898e-09],"iteration":901,"passed_time":2.906459565,"remaining_time":0.3157794206},
{"learn":[1.386552288e-09],"iteration":902,"passed_time":2.908296256,"remaining_time":0.3124083464},
{"learn":[1.343737724e-09],"iteration":903,"passed_time":2.91000495,"remaining_time":0.3090270743},
{"learn":[1.316409839e-09],"iteration":904,"passed_time":2.912992029,"remaining_time":0.3057836937},
{"learn":[1.289371953e-09],"iteration":905,"passed_time":2.914671607,"remaining_time":0.3024052219},
{"learn":[1.256810263e-09],"iteration":906,"passed_time":2.917389621,"remaining_time":0.2991369733},
{"learn":[1.226731928e-09],"iteration":907,"passed_time":2.919141878,"remaining_time":0.2957720846},
{"learn":[1.18938506e-09],"iteration":908,"passed_time":2.924164122,"remaining_time":0.2927381025},
{"learn":[1.164101014e-09],"iteration":909,"passed_time":2.925688142,"remaining_time":0.2893537723},
{"learn":[1.145219284e-09],"iteration":910,"passed_time":2.928633409,"remaining_time":0.2861123748},
{"learn":[1.127140275e-09],"iteration":911,"passed_time":2.93046884,"remaining_time":0.2827645372},
{"learn":[1.106290034e-09],"iteration":912,"passed_time":2.939628675,"remaining_time":0.280117957},
{"learn":[1.067028705e-09],"iteration":913,"passed_time":2.941878732,"remaining_time":0.2768069704},
{"learn":[1.037663647e-09],"iteration":914,"passed_time":2.943824932,"remaining_time":0.2734700757},
{"learn":[1.009323159e-09],"iteration":915,"passed_time":2.948169121,"remaining_time":0.2703561202},
{"learn":[9.822269478e-10],"iteration":916,"passed_time":2.950551138,"remaining_time":0.2670618806},
{"learn":[9.557980996e-10],"iteration":917,"passed_time":2.952406912,"remaining_time":0.2637226218},
{"learn":[9.380646334e-10],"iteration":918,"passed_time":2.955492336,"remaining_time":0.2604949719},
{"learn":[9.049790685e-10],"iteration":919,"passed_time":2.96631489,"remaining_time":0.2579404252},
{"learn":[8.803115153e-10],"iteration":920,"passed_time":2.967958762,"remaining_time":0.2545806104},
{"learn":[8.565034827e-10],"iteration":921,"passed_time":2.972224592,"remaining_time":0.251446332},
{"learn":[8.335262894e-10],"iteration":922,"passed_time":2.98228282,"remaining_time":0.2487928246},
{"learn":[8.14626042e-10],"iteration":923,"passed_time":2.983919306,"remaining_time":0.2454305923},
{"learn":[7.965931013e-10],"iteration":924,"passed_time":2.985714991,"remaining_time":0.2420849993},
{"learn":[7.727180174e-10],"iteration":925,"passed_time":2.987677394,"remaining_time":0.2387560768},
{"learn":[7.514286843e-10],"iteration":926,"passed_time":2.991709016,"remaining_time":0.2355930509},
{"learn":[7.364446981e-10],"iteration":927,"passed_time":2.994231838,"remaining_time":0.2323110909},
{"learn":[7.22879678e-10],"iteration":928,"passed_time":2.995803802,"remaining_time":0.2289580946},
{"learn":[7.09777948e-10],"iteration":929,"passed_time":2.997497478,"remaining_time":0.2256180898},
{"learn":[6.870750018e-10],"iteration":930,"passed_time":3.001270386,"remaining_time":0.2224357214},
{"learn":[6.682732461e-10],"iteration":931,"passed_time":3.003569379,"remaining_time":0.2191445469},
{"learn":[6.485279482e-10],"iteration":932,"passed_time":3.006175751,"remaining_time":0.2158775727},
{"learn":[6.368095697e-10],"iteration":933,"passed_time":3.009325564,"remaining_time":0.2126504146},
{"learn":[6.220768337e-10],"iteration":934,"passed_time":3.019725022,"remaining_time":0.2099274079},
{"learn":[6.027150933e-10],"iteration":935,"passed_time":3.021336764,"remaining_time":0.2065871292},
{"learn":[5.922016087e-10],"iteration":936,"passed_time":3.022846567,"remaining_time":0.2032436859},
{"learn":[5.741781865e-10],"iteration":937,"passed_time":3.028945541,"remaining_time":0.2002074878},
{"learn":[5.589253947e-10],"iteration":938,"passed_time":3.030859813,"remaining_time":0.1968929165},
{"learn":[5.438208761e-10],"iteration":939,"passed_time":3.033262753,"remaining_time":0.1936125162},
{"learn":[5.299538612e-10],"iteration":940,"passed_time":3.035129758,"remaining_time":0.190300378},
{"learn":[5.166454739e-10],"iteration":941,"passed_time":3.036654109,"remaining_time":0.1869702106},
{"learn":[5.024467693e-10],"iteration":942,"passed_time":3.040001112,"remaining_time":0.1837540439},
{"learn":[4.901619836e-10],"iteration":943,"passed_time":3.042534582,"remaining_time":0.1804893396},
{"learn":[4.779441182e-10],"iteration":944,"passed_time":3.044367996,"remaining_time":0.1771854389},
{"learn":[4.662654784e-10],"iteration":945,"passed_time":3.04600921,"remaining_time":0.1738736758},
{"learn":[4.558668331e-10],"iteration":946,"passed_time":3.048195844,"remaining_time":0.1705959659},
{"learn":[4.439952256e-10],"iteration":947,"passed_time":3.054347529,"remaining_time":0.1675380501},
{"learn":[4.333046426e-10],"iteration":948,"passed_time":3.056791569,"remaining_time":0.1642743625},
{"learn":[4.227557951e-10],"iteration":949,"passed_time":3.0586536,"remaining_time":0.1609817684},
{"learn":[4.127140906e-10],"iteration":950,"passed_time":3.063284785,"remaining_time":0.1578348628},
{"learn":[4.03151741e-10],"iteration":951,"passed_time":3.066498424,"remaining_time":0.1546133659},
{"learn":[3.936347088e-10],"iteration":952,"passed_time":3.068323352,"remaining_time":0.1513233972},
{"learn":[3.847133319e-10],"iteration":953,"passed_time":3.070951139,"remaining_time":0.1480752122},
{"learn":[3.762120391e-10],"iteration":954,"passed_time":3.078407064,"remaining_time":0.1450558302},
{"learn":[3.675546489e-10],"iteration":955,"passed_time":3.080304573,"remaining_time":0.1417713402},
{"learn":[3.584187922e-10],"iteration":956,"passed_time":3.083187588,"remaining_time":0.1385340296},
{"learn":[3.485461675e-10],"iteration":957,"passed_time":3.084715152,"remaining_time":0.1352380338},
{"learn":[3.409797892e-10],"iteration":958,"passed_time":3.089684026,"remaining_time":0.132092852},
{"learn":[3.328438228e-10],"iteration":959,"passed_time":3.091917174,"remaining_time":0.1288298823},
{"learn":[3.243931679e-10],"iteration":960,"passed_time":3.093670875,"remaining_time":0.1255495985},
{"learn":[3.160775853e-10],"iteration":961,"passed_time":3.098783865,"remaining_time":0.1224051839},
{"learn":[3.082102891e-10],"iteration":962,"passed_time":3.10058233,"remaining_time":0.1191293315},
{"learn":[3.007703575e-10],"iteration":963,"passed_time":3.102336528,"remaining_time":0.1158548911},
{"learn":[2.940130454e-10],"iteration":964,"passed_time":3.10520053,"remaining_time":0.1126238534},
{"learn":[2.876450508e-10],"iteration":965,"passed_time":3.10699468,"remaining_time":0.1093559204},
{"learn":[2.83454937e-10],"iteration":966,"passed_time":3.115778739,"remaining_time":0.1063295743},
{"learn":[2.758706543e-10],"iteration":967,"passed_time":3.122097538,"remaining_time":0.103209836},
{"learn":[2.720104198e-10],"iteration":968,"passed_time":3.128117602,"remaining_time":0.1000739377},
{"learn":[2.648988439e-10],"iteration":969,"passed_time":3.129800411,"remaining_time":0.09679795086},
{"learn":[2.589556069e-10],"iteration":970,"passed_time":3.131414431,"remaining_time":0.09352319104},
{"learn":[2.513978565e-10],"iteration":971,"passed_time":3.13399362,"remaining_time":0.0902796516},
{"learn":[2.443996304e-10],"iteration":972,"passed_time":3.135899499,"remaining_time":0.08701879391},
{"learn":[2.374284376e-10],"iteration":973,"passed_time":3.137594298,"remaining_time":0.08375508393},
{"learn":[2.307645679e-10],"iteration":974,"passed_time":3.159238213,"remaining_time":0.08100610803},
{"learn":[2.247852875e-10],"iteration":975,"passed_time":3.160928147,"remaining_time":0.07772774131},
{"learn":[2.185119873e-10],"iteration":976,"passed_time":3.162814338,"remaining_time":0.07445724644},
{"learn":[2.123507356e-10],"iteration":977,"passed_time":3.166068537,"remaining_time":0.07122035563},
{"learn":[2.064590674e-10],"iteration":978,"passed_time":3.176655625,"remaining_time":0.06814072331},
{"learn":[2.008253967e-10],"iteration":979,"passed_time":3.179136967,"remaining_time":0.06488034626},
{"learn":[1.984254755e-10],"iteration":980,"passed_time":3.180069093,"remaining_time":0.06159155226},
{"learn":[1.928069723e-10],"iteration":981,"passed_time":3.18354833,"remaining_time":0.05835424638},
{"learn":[1.897528262e-10],"iteration":982,"passed_time":3.185575292,"remaining_time":0.05509133262},
{"learn":[1.846067546e-10],"iteration":983,"passed_time":3.187840117,"remaining_time":0.05183479865},
{"learn":[1.796854242e-10],"iteration":984,"passed_time":3.198597252,"remaining_time":0.04870960282},
{"learn":[1.752391519e-10],"iteration":985,"passed_time":3.201961658,"remaining_time":0.04546395863},
{"learn":[1.702629168e-10],"iteration":986,"passed_time":3.203673982,"remaining_time":0.04219631385},
{"learn":[1.684339095e-10],"iteration":987,"passed_time":3.205574899,"remaining_time":0.03893410809},
{"learn":[1.656775329e-10],"iteration":988,"passed_time":3.209100616,"remaining_time":0.03569272677},
{"learn":[1.631313673e-10],"iteration":989,"passed_time":3.212483134,"remaining_time":0.03244932459},
{"learn":[1.608384505e-10],"iteration":990,"passed_time":3.215946471,"remaining_time":0.02920637562},
{"learn":[1.564986752e-10],"iteration":991,"passed_time":3.217521318,"remaining_time":0.02594775257},
{"learn":[1.526229446e-10],"iteration":992,"passed_time":3.219208719,"remaining_time":0.02269331423},
{"learn":[1.485741505e-10],"iteration":993,"passed_time":3.220935517,"remaining_time":0.0194422667},
{"learn":[1.443487763e-10],"iteration":994,"passed_time":3.227809429,"remaining_time":0.01622014788},
{"learn":[1.403718327e-10],"iteration":995,"passed_time":3.234811177,"remaining_time":0.01299120955},
{"learn":[1.364642729e-10],"iteration":996,"passed_time":3.236331868,"remaining_time":0.009738210234},
{"learn":[1.329320253e-10],"iteration":997,"passed_time":3.239035445,"remaining_time":0.006491052996},
{"learn":[1.294471078e-10],"iteration":998,"passed_time":3.240754062,"remaining_time":0.00324399806},
{"learn":[1.257438792e-10],"iteration":999,"passed_time":3.243396521,"remaining_time":0}
]}